{"DIVINE_IMMORTAL": {"vs": {"94": {"win_rate": 0.598, "games": 199}, "137": {"win_rate": 0.586, "games": 338}, "4": {"win_rate": 0.579, "games": 164}, "58": {"win_rate": 0.6, "games": 140}, "45": {"win_rate": 0.569, "games": 188}, "103": {"win_rate": 0.561, "games": 57}, "113": {"win_rate": 0.581, "games": 160}, "49": {"win_rate": 0.598, "games": 132}, "138": {"win_rate": 0.583, "games": 436}, "56": {"win_rate": 0.539, "games": 269}, "112": {"win_rate": 0.53, "games": 411}, "52": {"win_rate": 0.563, "games": 238}, "3": {"win_rate": 0.536, "games": 196}, "84": {"win_rate": 0.556, "games": 527}, "2": {"win_rate": 0.542, "games": 712}, "48": {"win_rate": 0.54, "games": 500}, "83": {"win_rate": 0.525, "games": 198}, "88": {"win_rate": 0.527, "games": 336}, "98": {"win_rate": 0.608, "games": 166}, "35": {"win_rate": 0.57, "games": 532}, "7": {"win_rate": 0.546, "games": 665}, "69": {"win_rate": 0.574, "games": 542}, "114": {"win_rate": 0.568, "games": 701}, "85": {"win_rate": 0.52, "games": 479}, "46": {"win_rate": 0.602, "games": 259}, "108": {"win_rate": 0.552, "games": 359}, "82": {"win_rate": 0.535, "games": 157}, "21": {"win_rate": 0.548, "games": 485}, "121": {"win_rate": 0.519, "games": 343}, "78": {"win_rate": 0.516, "games": 126}, "75": {"win_rate": 0.547, "games": 477}, "131": {"win_rate": 0.55, "games": 413}, "6": {"win_rate": 0.534, "games": 468}, "51": {"win_rate": 0.534, "games": 176}, "37": {"win_rate": 0.558, "games": 473}, "19": {"win_rate": 0.569, "games": 599}, "27": {"win_rate": 0.516, "games": 824}, "23": {"win_rate": 0.541, "games": 218}, "73": {"win_rate": 0.538, "games": 1053}, "14": {"win_rate": 0.542, "games": 1728}, "34": {"win_rate": 0.589, "games": 207}, "104": {"win_rate": 0.519, "games": 659}, "129": {"win_rate": 0.591, "games": 597}, "54": {"win_rate": 0.51, "games": 726}, "31": {"win_rate": 0.53, "games": 805}, "50": {"win_rate": 0.52, "games": 225}, "77": {"win_rate": 0.53, "games": 66}, "57": {"win_rate": 0.528, "games": 159}, "5": {"win_rate": 0.534, "games": 537}, "145": {"win_rate": 0.543, "games": 322}, "28": {"win_rate": 0.521, "games": 530}, "22": {"win_rate": 0.529, "games": 799}, "55": {"win_rate": 0.532, "games": 109}, "71": {"win_rate": 0.532, "games": 1033}, "30": {"win_rate": 0.545, "games": 690}, "62": {"win_rate": 0.502, "games": 253}, "16": {"win_rate": 0.563, "games": 396}, "120": {"win_rate": 0.53, "games": 857}, "100": {"win_rate": 0.53, "games": 611}, "87": {"win_rate": 0.528, "games": 544}, "97": {"win_rate": 0.535, "games": 736}, "42": {"win_rate": 0.514, "games": 477}, "59": {"win_rate": 0.505, "games": 378}, "126": {"win_rate": 0.533, "games": 640}, "86": {"win_rate": 0.509, "games": 1610}, "91": {"win_rate": 0.5, "games": 346}, "74": {"win_rate": 0.487, "games": 1227}, "135": {"win_rate": 0.485, "games": 655}, "44": {"win_rate": 0.528, "games": 530}, "102": {"win_rate": 0.507, "games": 203}, "106": {"win_rate": 0.515, "games": 627}, "17": {"win_rate": 0.543, "games": 532}, "53": {"win_rate": 0.553, "games": 262}, "155": {"win_rate": 0.518, "games": 141}, "33": {"win_rate": 0.493, "games": 148}, "89": {"win_rate": 0.511, "games": 94}, "63": {"win_rate": 0.541, "games": 560}, "99": {"win_rate": 0.535, "games": 419}, "11": {"win_rate": 0.534, "games": 686}, "80": {"win_rate": 0.473, "games": 222}, "43": {"win_rate": 0.516, "games": 314}, "93": {"win_rate": 0.512, "games": 1126}, "47": {"win_rate": 0.509, "games": 322}, "32": {"win_rate": 0.491, "games": 230}, "15": {"win_rate": 0.528, "games": 284}, "36": {"win_rate": 0.511, "games": 589}, "110": {"win_rate": 0.476, "games": 723}, "101": {"win_rate": 0.531, "games": 597}, "95": {"win_rate": 0.522, "games": 69}, "61": {"win_rate": 0.507, "games": 144}, "39": {"win_rate": 0.506, "games": 1215}, "70": {"win_rate": 0.522, "games": 406}, "8": {"win_rate": 0.492, "games": 581}, "64": {"win_rate": 0.544, "games": 540}, "60": {"win_rate": 0.475, "games": 583}, "128": {"win_rate": 0.519, "games": 422}, "96": {"win_rate": 0.54, "games": 226}, "105": {"win_rate": 0.475, "games": 617}, "26": {"win_rate": 0.51, "games": 1435}, "81": {"win_rate": 0.511, "games": 131}, "92": {"win_rate": 0.421, "games": 152}, "123": {"win_rate": 0.506, "games": 619}, "1": {"win_rate": 0.52, "games": 446}, "40": {"win_rate": 0.514, "games": 798}, "136": {"win_rate": 0.503, "games": 296}, "119": {"win_rate": 0.503, "games": 312}, "107": {"win_rate": 0.478, "games": 318}, "68": {"win_rate": 0.511, "games": 333}, "25": {"win_rate": 0.49, "games": 594}, "72": {"win_rate": 0.546, "games": 194}, "41": {"win_rate": 0.483, "games": 557}, "38": {"win_rate": 0.485, "games": 579}, "111": {"win_rate": 0.471, "games": 225}, "18": {"win_rate": 0.481, "games": 135}, "79": {"win_rate": 0.507, "games": 294}, "90": {"win_rate": 0.452, "games": 445}, "13": {"win_rate": 0.489, "games": 413}, "12": {"win_rate": 0.44, "games": 554}, "76": {"win_rate": 0.489, "games": 227}, "10": {"win_rate": 0.496, "games": 274}, "109": {"win_rate": 0.442, "games": 240}, "20": {"win_rate": 0.45, "games": 380}, "29": {"win_rate": 0.459, "games": 1095}, "67": {"win_rate": 0.459, "games": 303}, "66": {"win_rate": 0.447, "games": 38}, "9": {"win_rate": 0.431, "games": 313}}, "with": {"81": {"win_rate": 0.623, "games": 106}, "76": {"win_rate": 0.578, "games": 166}, "61": {"win_rate": 0.58, "games": 100}, "43": {"win_rate": 0.577, "games": 168}, "66": {"win_rate": 0.569, "games": 58}, "48": {"win_rate": 0.587, "games": 567}, "113": {"win_rate": 0.577, "games": 137}, "121": {"win_rate": 0.593, "games": 302}, "83": {"win_rate": 0.592, "games": 218}, "109": {"win_rate": 0.597, "games": 258}, "112": {"win_rate": 0.601, "games": 301}, "46": {"win_rate": 0.51, "games": 296}, "90": {"win_rate": 0.59, "games": 322}, "72": {"win_rate": 0.5, "games": 152}, "131": {"win_rate": 0.554, "games": 327}, "108": {"win_rate": 0.553, "games": 179}, "20": {"win_rate": 0.58, "games": 288}, "7": {"win_rate": 0.558, "games": 547}, "11": {"win_rate": 0.535, "games": 565}, "6": {"win_rate": 0.563, "games": 490}, "86": {"win_rate": 0.565, "games": 1328}, "104": {"win_rate": 0.569, "games": 320}, "101": {"win_rate": 0.528, "games": 527}, "67": {"win_rate": 0.561, "games": 321}, "155": {"win_rate": 0.55, "games": 109}, "110": {"win_rate": 0.579, "games": 558}, "92": {"win_rate": 0.624, "games": 93}, "32": {"win_rate": 0.566, "games": 166}, "10": {"win_rate": 0.523, "games": 310}, "64": {"win_rate": 0.5, "games": 472}, "84": {"win_rate": 0.537, "games": 484}, "107": {"win_rate": 0.551, "games": 283}, "138": {"win_rate": 0.523, "games": 438}, "51": {"win_rate": 0.543, "games": 173}, "89": {"win_rate": 0.538, "games": 91}, "88": {"win_rate": 0.554, "games": 361}, "40": {"win_rate": 0.513, "games": 631}, "135": {"win_rate": 0.565, "games": 423}, "55": {"win_rate": 0.531, "games": 49}, "17": {"win_rate": 0.506, "games": 352}, "94": {"win_rate": 0.533, "games": 197}, "79": {"win_rate": 0.502, "games": 205}, "63": {"win_rate": 0.504, "games": 450}, "100": {"win_rate": 0.524, "games": 626}, "37": {"win_rate": 0.513, "games": 390}, "128": {"win_rate": 0.512, "games": 334}, "22": {"win_rate": 0.531, "games": 655}, "74": {"win_rate": 0.559, "games": 900}, "4": {"win_rate": 0.545, "games": 178}, "47": {"win_rate": 0.528, "games": 193}, "93": {"win_rate": 0.525, "games": 886}, "62": {"win_rate": 0.551, "games": 256}, "26": {"win_rate": 0.516, "games": 1139}, "12": {"win_rate": 0.562, "games": 568}, "136": {"win_rate": 0.516, "games": 258}, "23": {"win_rate": 0.523, "games": 172}, "29": {"win_rate": 0.535, "games": 527}, "99": {"win_rate": 0.504, "games": 252}, "111": {"win_rate": 0.533, "games": 229}, "77": {"win_rate": 0.526, "games": 38}, "78": {"win_rate": 0.548, "games": 73}, "9": {"win_rate": 0.518, "games": 274}, "123": {"win_rate": 0.513, "games": 458}, "71": {"win_rate": 0.518, "games": 984}, "87": {"win_rate": 0.517, "games": 451}, "137": {"win_rate": 0.532, "games": 203}, "39": {"win_rate": 0.519, "games": 771}, "145": {"win_rate": 0.508, "games": 295}, "75": {"win_rate": 0.514, "games": 434}, "41": {"win_rate": 0.517, "games": 482}, "14": {"win_rate": 0.512, "games": 1374}, "85": {"win_rate": 0.543, "games": 435}, "58": {"win_rate": 0.505, "games": 111}, "106": {"win_rate": 0.517, "games": 509}, "13": {"win_rate": 0.503, "games": 296}, "19": {"win_rate": 0.487, "games": 474}, "18": {"win_rate": 0.512, "games": 166}, "96": {"win_rate": 0.475, "games": 120}, "114": {"win_rate": 0.492, "games": 650}, "82": {"win_rate": 0.521, "games": 144}, "91": {"win_rate": 0.53, "games": 296}, "5": {"win_rate": 0.509, "games": 475}, "54": {"win_rate": 0.534, "games": 809}, "52": {"win_rate": 0.51, "games": 210}, "38": {"win_rate": 0.505, "games": 430}, "31": {"win_rate": 0.512, "games": 640}, "56": {"win_rate": 0.535, "games": 230}, "1": {"win_rate": 0.482, "games": 407}, "8": {"win_rate": 0.518, "games": 542}, "50": {"win_rate": 0.52, "games": 202}, "57": {"win_rate": 0.509, "games": 106}, "42": {"win_rate": 0.512, "games": 404}, "69": {"win_rate": 0.476, "games": 357}, "70": {"win_rate": 0.485, "games": 445}, "68": {"win_rate": 0.481, "games": 287}, "44": {"win_rate": 0.491, "games": 532}, "16": {"win_rate": 0.465, "games": 243}, "105": {"win_rate": 0.525, "games": 549}, "73": {"win_rate": 0.499, "games": 846}, "30": {"win_rate": 0.483, "games": 522}, "119": {"win_rate": 0.489, "games": 272}, "36": {"win_rate": 0.496, "games": 419}, "35": {"win_rate": 0.476, "games": 441}, "34": {"win_rate": 0.446, "games": 157}, "102": {"win_rate": 0.508, "games": 128}, "120": {"win_rate": 0.493, "games": 590}, "80": {"win_rate": 0.535, "games": 200}, "33": {"win_rate": 0.518, "games": 83}, "25": {"win_rate": 0.487, "games": 470}, "21": {"win_rate": 0.49, "games": 388}, "2": {"win_rate": 0.504, "games": 421}, "98": {"win_rate": 0.432, "games": 111}, "103": {"win_rate": 0.514, "games": 70}, "15": {"win_rate": 0.47, "games": 183}, "28": {"win_rate": 0.497, "games": 290}, "59": {"win_rate": 0.504, "games": 252}, "129": {"win_rate": 0.429, "games": 310}, "45": {"win_rate": 0.5, "games": 124}, "126": {"win_rate": 0.467, "games": 452}, "27": {"win_rate": 0.501, "games": 749}, "60": {"win_rate": 0.498, "games": 307}, "97": {"win_rate": 0.458, "games": 483}, "53": {"win_rate": 0.428, "games": 208}, "95": {"win_rate": 0.443, "games": 79}, "49": {"win_rate": 0.425, "games": 120}, "3": {"win_rate": 0.452, "games": 168}}}, "LEGEND_ANCIENT": {"vs": {"95": {"win_rate": 0.618, "games": 89}, "18": {"win_rate": 0.596, "games": 193}, "83": {"win_rate": 0.583, "games": 168}, "155": {"win_rate": 0.608, "games": 125}, "36": {"win_rate": 0.558, "games": 891}, "80": {"win_rate": 0.531, "games": 213}, "55": {"win_rate": 0.556, "games": 99}, "112": {"win_rate": 0.542, "games": 288}, "60": {"win_rate": 0.533, "games": 597}, "46": {"win_rate": 0.587, "games": 327}, "6": {"win_rate": 0.547, "games": 658}, "23": {"win_rate": 0.554, "games": 312}, "114": {"win_rate": 0.576, "games": 623}, "66": {"win_rate": 0.575, "games": 40}, "135": {"win_rate": 0.511, "games": 650}, "56": {"win_rate": 0.513, "games": 312}, "138": {"win_rate": 0.548, "games": 405}, "72": {"win_rate": 0.596, "games": 225}, "68": {"win_rate": 0.554, "games": 424}, "136": {"win_rate": 0.544, "games": 305}, "98": {"win_rate": 0.601, "games": 183}, "74": {"win_rate": 0.499, "games": 1493}, "78": {"win_rate": 0.515, "games": 97}, "87": {"win_rate": 0.539, "games": 577}, "22": {"win_rate": 0.529, "games": 913}, "105": {"win_rate": 0.512, "games": 723}, "108": {"win_rate": 0.528, "games": 341}, "2": {"win_rate": 0.508, "games": 1057}, "123": {"win_rate": 0.534, "games": 698}, "109": {"win_rate": 0.531, "games": 192}, "120": {"win_rate": 0.53, "games": 705}, "7": {"win_rate": 0.52, "games": 864}, "1": {"win_rate": 0.546, "games": 681}, "9": {"win_rate": 0.529, "games": 459}, "85": {"win_rate": 0.5, "games": 556}, "43": {"win_rate": 0.537, "games": 307}, "25": {"win_rate": 0.537, "games": 784}, "106": {"win_rate": 0.531, "games": 548}, "131": {"win_rate": 0.538, "games": 303}, "13": {"win_rate": 0.551, "games": 372}, "67": {"win_rate": 0.491, "games": 581}, "37": {"win_rate": 0.524, "games": 628}, "54": {"win_rate": 0.49, "games": 896}, "128": {"win_rate": 0.547, "games": 433}, "51": {"win_rate": 0.54, "games": 150}, "47": {"win_rate": 0.523, "games": 363}, "100": {"win_rate": 0.534, "games": 513}, "88": {"win_rate": 0.505, "games": 390}, "129": {"win_rate": 0.571, "games": 630}, "35": {"win_rate": 0.524, "games": 1027}, "137": {"win_rate": 0.506, "games": 354}, "86": {"win_rate": 0.506, "games": 1637}, "62": {"win_rate": 0.492, "games": 240}, "53": {"win_rate": 0.568, "games": 403}, "28": {"win_rate": 0.503, "games": 545}, "50": {"win_rate": 0.498, "games": 327}, "16": {"win_rate": 0.528, "games": 432}, "59": {"win_rate": 0.514, "games": 370}, "19": {"win_rate": 0.558, "games": 486}, "73": {"win_rate": 0.504, "games": 1015}, "145": {"win_rate": 0.528, "games": 322}, "90": {"win_rate": 0.487, "games": 392}, "34": {"win_rate": 0.564, "games": 250}, "4": {"win_rate": 0.487, "games": 234}, "29": {"win_rate": 0.485, "games": 1070}, "14": {"win_rate": 0.511, "games": 1880}, "11": {"win_rate": 0.525, "games": 918}, "75": {"win_rate": 0.51, "games": 686}, "69": {"win_rate": 0.543, "games": 610}, "64": {"win_rate": 0.54, "games": 682}, "49": {"win_rate": 0.518, "games": 195}, "81": {"win_rate": 0.513, "games": 199}, "44": {"win_rate": 0.512, "games": 763}, "61": {"win_rate": 0.494, "games": 178}, "15": {"win_rate": 0.511, "games": 360}, "8": {"win_rate": 0.486, "games": 836}, "93": {"win_rate": 0.503, "games": 1108}, "63": {"win_rate": 0.535, "games": 630}, "5": {"win_rate": 0.496, "games": 682}, "3": {"win_rate": 0.482, "games": 168}, "48": {"win_rate": 0.491, "games": 546}, "12": {"win_rate": 0.463, "games": 534}, "57": {"win_rate": 0.511, "games": 184}, "40": {"win_rate": 0.516, "games": 913}, "42": {"win_rate": 0.465, "games": 767}, "26": {"win_rate": 0.503, "games": 1840}, "126": {"win_rate": 0.496, "games": 502}, "33": {"win_rate": 0.486, "games": 146}, "99": {"win_rate": 0.503, "games": 485}, "30": {"win_rate": 0.492, "games": 1100}, "41": {"win_rate": 0.491, "games": 636}, "97": {"win_rate": 0.499, "games": 916}, "91": {"win_rate": 0.48, "games": 246}, "84": {"win_rate": 0.486, "games": 895}, "70": {"win_rate": 0.511, "games": 487}, "119": {"win_rate": 0.503, "games": 338}, "45": {"win_rate": 0.479, "games": 257}, "10": {"win_rate": 0.513, "games": 335}, "39": {"win_rate": 0.493, "games": 1161}, "71": {"win_rate": 0.486, "games": 1240}, "102": {"win_rate": 0.477, "games": 260}, "27": {"win_rate": 0.464, "games": 1007}, "31": {"win_rate": 0.47, "games": 915}, "82": {"win_rate": 0.467, "games": 184}, "58": {"win_rate": 0.5, "games": 110}, "21": {"win_rate": 0.492, "games": 630}, "113": {"win_rate": 0.458, "games": 225}, "110": {"win_rate": 0.442, "games": 627}, "104": {"win_rate": 0.445, "games": 994}, "121": {"win_rate": 0.449, "games": 374}, "107": {"win_rate": 0.454, "games": 280}, "20": {"win_rate": 0.438, "games": 553}, "38": {"win_rate": 0.494, "games": 573}, "52": {"win_rate": 0.478, "games": 247}, "77": {"win_rate": 0.452, "games": 62}, "32": {"win_rate": 0.439, "games": 244}, "96": {"win_rate": 0.493, "games": 268}, "101": {"win_rate": 0.475, "games": 767}, "111": {"win_rate": 0.451, "games": 284}, "79": {"win_rate": 0.507, "games": 217}, "89": {"win_rate": 0.45, "games": 100}, "103": {"win_rate": 0.429, "games": 56}, "17": {"win_rate": 0.484, "games": 545}, "94": {"win_rate": 0.438, "games": 276}, "76": {"win_rate": 0.459, "games": 281}, "92": {"win_rate": 0.369, "games": 103}}, "with": {"57": {"win_rate": 0.593, "games": 145}, "33": {"win_rate": 0.585, "games": 118}, "46": {"win_rate": 0.525, "games": 362}, "90": {"win_rate": 0.58, "games": 317}, "120": {"win_rate": 0.554, "games": 513}, "121": {"win_rate": 0.575, "games": 327}, "66": {"win_rate": 0.528, "games": 36}, "45": {"win_rate": 0.558, "games": 163}, "51": {"win_rate": 0.528, "games": 163}, "91": {"win_rate": 0.556, "games": 268}, "80": {"win_rate": 0.582, "games": 146}, "94": {"win_rate": 0.553, "games": 284}, "68": {"win_rate": 0.525, "games": 295}, "102": {"win_rate": 0.549, "games": 182}, "21": {"win_rate": 0.526, "games": 477}, "64": {"win_rate": 0.507, "games": 602}, "78": {"win_rate": 0.558, "games": 86}, "25": {"win_rate": 0.529, "games": 639}, "59": {"win_rate": 0.535, "games": 284}, "145": {"win_rate": 0.519, "games": 235}, "18": {"win_rate": 0.535, "games": 215}, "69": {"win_rate": 0.497, "games": 328}, "138": {"win_rate": 0.521, "games": 376}, "8": {"win_rate": 0.548, "games": 777}, "34": {"win_rate": 0.478, "games": 178}, "72": {"win_rate": 0.472, "games": 199}, "43": {"win_rate": 0.519, "games": 214}, "101": {"win_rate": 0.516, "games": 608}, "53": {"win_rate": 0.476, "games": 315}, "40": {"win_rate": 0.511, "games": 745}, "82": {"win_rate": 0.541, "games": 159}, "99": {"win_rate": 0.52, "games": 333}, "11": {"win_rate": 0.511, "games": 716}, "60": {"win_rate": 0.551, "games": 354}, "4": {"win_rate": 0.548, "games": 208}, "61": {"win_rate": 0.536, "games": 151}, "31": {"win_rate": 0.539, "games": 750}, "7": {"win_rate": 0.532, "games": 630}, "16": {"win_rate": 0.509, "games": 271}, "93": {"win_rate": 0.523, "games": 1011}, "97": {"win_rate": 0.515, "games": 620}, "100": {"win_rate": 0.507, "games": 495}, "32": {"win_rate": 0.543, "games": 243}, "83": {"win_rate": 0.525, "games": 141}, "6": {"win_rate": 0.523, "games": 621}, "128": {"win_rate": 0.491, "games": 346}, "135": {"win_rate": 0.548, "games": 420}, "47": {"win_rate": 0.513, "games": 238}, "44": {"win_rate": 0.507, "games": 764}, "10": {"win_rate": 0.49, "games": 308}, "19": {"win_rate": 0.469, "games": 439}, "86": {"win_rate": 0.522, "games": 1371}, "111": {"win_rate": 0.522, "games": 228}, "119": {"win_rate": 0.498, "games": 227}, "20": {"win_rate": 0.54, "games": 400}, "75": {"win_rate": 0.507, "games": 568}, "52": {"win_rate": 0.497, "games": 175}, "108": {"win_rate": 0.511, "games": 184}, "27": {"win_rate": 0.529, "games": 902}, "37": {"win_rate": 0.506, "games": 451}, "5": {"win_rate": 0.514, "games": 621}, "79": {"win_rate": 0.462, "games": 173}, "85": {"win_rate": 0.533, "games": 486}, "26": {"win_rate": 0.502, "games": 1436}, "39": {"win_rate": 0.501, "games": 849}, "38": {"win_rate": 0.481, "games": 432}, "84": {"win_rate": 0.511, "games": 741}, "2": {"win_rate": 0.527, "games": 679}, "42": {"win_rate": 0.538, "games": 638}, "129": {"win_rate": 0.453, "games": 358}, "28": {"win_rate": 0.516, "games": 337}, "74": {"win_rate": 0.54, "games": 1028}, "107": {"win_rate": 0.52, "games": 250}, "54": {"win_rate": 0.535, "games": 950}, "30": {"win_rate": 0.507, "games": 937}, "105": {"win_rate": 0.521, "games": 576}, "77": {"win_rate": 0.514, "games": 37}, "110": {"win_rate": 0.533, "games": 465}, "88": {"win_rate": 0.513, "games": 341}, "48": {"win_rate": 0.511, "games": 470}, "12": {"win_rate": 0.538, "games": 611}, "9": {"win_rate": 0.498, "games": 321}, "126": {"win_rate": 0.501, "games": 413}, "23": {"win_rate": 0.495, "games": 194}, "112": {"win_rate": 0.514, "games": 243}, "106": {"win_rate": 0.491, "games": 426}, "14": {"win_rate": 0.495, "games": 1389}, "62": {"win_rate": 0.52, "games": 246}, "71": {"win_rate": 0.496, "games": 1100}, "89": {"win_rate": 0.504, "games": 129}, "41": {"win_rate": 0.499, "games": 613}, "22": {"win_rate": 0.497, "games": 694}, "29": {"win_rate": 0.518, "games": 666}, "114": {"win_rate": 0.466, "games": 668}, "50": {"win_rate": 0.505, "games": 281}, "136": {"win_rate": 0.481, "games": 270}, "67": {"win_rate": 0.518, "games": 550}, "76": {"win_rate": 0.474, "games": 209}, "36": {"win_rate": 0.499, "games": 577}, "70": {"win_rate": 0.464, "games": 528}, "35": {"win_rate": 0.478, "games": 797}, "81": {"win_rate": 0.476, "games": 143}, "49": {"win_rate": 0.47, "games": 181}, "87": {"win_rate": 0.476, "games": 479}, "15": {"win_rate": 0.475, "games": 236}, "131": {"win_rate": 0.468, "games": 269}, "17": {"win_rate": 0.447, "games": 387}, "56": {"win_rate": 0.504, "games": 246}, "113": {"win_rate": 0.491, "games": 161}, "103": {"win_rate": 0.5, "games": 54}, "73": {"win_rate": 0.48, "games": 858}, "13": {"win_rate": 0.444, "games": 275}, "98": {"win_rate": 0.406, "games": 138}, "63": {"win_rate": 0.439, "games": 519}, "155": {"win_rate": 0.448, "games": 116}, "1": {"win_rate": 0.449, "games": 662}, "55": {"win_rate": 0.47, "games": 66}, "92": {"win_rate": 0.522, "games": 90}, "104": {"win_rate": 0.489, "games": 536}, "123": {"win_rate": 0.454, "games": 485}, "137": {"win_rate": 0.466, "games": 234}, "3": {"win_rate": 0.474, "games": 133}, "95": {"win_rate": 0.439, "games": 98}, "96": {"win_rate": 0.404, "games": 166}, "109": {"win_rate": 0.423, "games": 196}, "58": {"win_rate": 0.383, "games": 94}}}, "CRUSADER_ARCHON": {"vs": {"98": {"win_rate": 0.634, "games": 216}, "103": {"win_rate": 0.56, "games": 75}, "137": {"win_rate": 0.549, "games": 328}, "46": {"win_rate": 0.593, "games": 440}, "70": {"win_rate": 0.584, "games": 615}, "18": {"win_rate": 0.551, "games": 276}, "131": {"win_rate": 0.563, "games": 270}, "34": {"win_rate": 0.601, "games": 301}, "58": {"win_rate": 0.556, "games": 144}, "19": {"win_rate": 0.583, "games": 494}, "113": {"win_rate": 0.525, "games": 324}, "90": {"win_rate": 0.515, "games": 441}, "87": {"win_rate": 0.542, "games": 552}, "136": {"win_rate": 0.544, "games": 316}, "10": {"win_rate": 0.553, "games": 347}, "4": {"win_rate": 0.509, "games": 279}, "138": {"win_rate": 0.539, "games": 449}, "43": {"win_rate": 0.543, "games": 335}, "126": {"win_rate": 0.516, "games": 469}, "92": {"win_rate": 0.472, "games": 125}, "61": {"win_rate": 0.51, "games": 288}, "2": {"win_rate": 0.494, "games": 1325}, "101": {"win_rate": 0.525, "games": 998}, "114": {"win_rate": 0.558, "games": 668}, "66": {"win_rate": 0.541, "games": 37}, "15": {"win_rate": 0.519, "games": 403}, "74": {"win_rate": 0.491, "games": 1734}, "68": {"win_rate": 0.521, "games": 461}, "67": {"win_rate": 0.472, "games": 733}, "36": {"win_rate": 0.496, "games": 1085}, "53": {"win_rate": 0.582, "games": 522}, "111": {"win_rate": 0.519, "games": 268}, "100": {"win_rate": 0.532, "games": 451}, "86": {"win_rate": 0.511, "games": 1715}, "35": {"win_rate": 0.512, "games": 1454}, "112": {"win_rate": 0.513, "games": 302}, "51": {"win_rate": 0.538, "games": 208}, "135": {"win_rate": 0.478, "games": 584}, "84": {"win_rate": 0.497, "games": 1315}, "105": {"win_rate": 0.482, "games": 867}, "37": {"win_rate": 0.502, "games": 663}, "155": {"win_rate": 0.524, "games": 145}, "7": {"win_rate": 0.509, "games": 992}, "110": {"win_rate": 0.477, "games": 663}, "123": {"win_rate": 0.516, "games": 748}, "88": {"win_rate": 0.49, "games": 453}, "108": {"win_rate": 0.487, "games": 380}, "32": {"win_rate": 0.479, "games": 359}, "14": {"win_rate": 0.5, "games": 2236}, "26": {"win_rate": 0.507, "games": 2295}, "85": {"win_rate": 0.48, "games": 717}, "99": {"win_rate": 0.501, "games": 639}, "145": {"win_rate": 0.514, "games": 278}, "23": {"win_rate": 0.499, "games": 357}, "93": {"win_rate": 0.499, "games": 1195}, "69": {"win_rate": 0.539, "games": 540}, "28": {"win_rate": 0.485, "games": 627}, "52": {"win_rate": 0.513, "games": 267}, "25": {"win_rate": 0.513, "games": 1000}, "73": {"win_rate": 0.486, "games": 980}, "95": {"win_rate": 0.49, "games": 147}, "13": {"win_rate": 0.518, "games": 367}, "56": {"win_rate": 0.478, "games": 410}, "106": {"win_rate": 0.505, "games": 517}, "44": {"win_rate": 0.491, "games": 1012}, "8": {"win_rate": 0.476, "games": 1113}, "63": {"win_rate": 0.527, "games": 713}, "83": {"win_rate": 0.5, "games": 194}, "22": {"win_rate": 0.484, "games": 1105}, "29": {"win_rate": 0.466, "games": 1094}, "1": {"win_rate": 0.512, "games": 867}, "120": {"win_rate": 0.499, "games": 587}, "55": {"win_rate": 0.496, "games": 117}, "89": {"win_rate": 0.484, "games": 157}, "45": {"win_rate": 0.479, "games": 282}, "40": {"win_rate": 0.503, "games": 1058}, "41": {"win_rate": 0.488, "games": 783}, "6": {"win_rate": 0.483, "games": 893}, "128": {"win_rate": 0.51, "games": 480}, "96": {"win_rate": 0.503, "games": 358}, "20": {"win_rate": 0.458, "games": 602}, "60": {"win_rate": 0.469, "games": 542}, "97": {"win_rate": 0.501, "games": 858}, "27": {"win_rate": 0.461, "games": 1301}, "81": {"win_rate": 0.483, "games": 236}, "102": {"win_rate": 0.469, "games": 256}, "54": {"win_rate": 0.457, "games": 1035}, "30": {"win_rate": 0.472, "games": 1535}, "49": {"win_rate": 0.492, "games": 317}, "71": {"win_rate": 0.478, "games": 1415}, "21": {"win_rate": 0.507, "games": 800}, "104": {"win_rate": 0.453, "games": 1380}, "42": {"win_rate": 0.439, "games": 1045}, "64": {"win_rate": 0.514, "games": 862}, "5": {"win_rate": 0.469, "games": 878}, "12": {"win_rate": 0.436, "games": 743}, "109": {"win_rate": 0.485, "games": 227}, "121": {"win_rate": 0.46, "games": 398}, "80": {"win_rate": 0.433, "games": 238}, "11": {"win_rate": 0.496, "games": 1074}, "119": {"win_rate": 0.495, "games": 331}, "57": {"win_rate": 0.48, "games": 198}, "79": {"win_rate": 0.511, "games": 186}, "76": {"win_rate": 0.483, "games": 358}, "16": {"win_rate": 0.476, "games": 485}, "62": {"win_rate": 0.471, "games": 310}, "9": {"win_rate": 0.469, "games": 503}, "3": {"win_rate": 0.464, "games": 183}, "75": {"win_rate": 0.46, "games": 860}, "91": {"win_rate": 0.443, "games": 334}, "48": {"win_rate": 0.449, "games": 604}, "82": {"win_rate": 0.453, "games": 212}, "50": {"win_rate": 0.448, "games": 391}, "39": {"win_rate": 0.478, "games": 1137}, "107": {"win_rate": 0.458, "games": 273}, "47": {"win_rate": 0.468, "games": 528}, "94": {"win_rate": 0.446, "games": 361}, "17": {"win_rate": 0.488, "games": 582}, "31": {"win_rate": 0.434, "games": 904}, "38": {"win_rate": 0.47, "games": 723}, "33": {"win_rate": 0.444, "games": 216}, "129": {"win_rate": 0.494, "games": 607}, "78": {"win_rate": 0.432, "games": 111}, "59": {"win_rate": 0.436, "games": 452}, "77": {"win_rate": 0.456, "games": 68}, "72": {"win_rate": 0.464, "games": 224}}, "with": {"103": {"win_rate": 0.592, "games": 49}, "155": {"win_rate": 0.551, "games": 136}, "59": {"win_rate": 0.557, "games": 332}, "83": {"win_rate": 0.553, "games": 161}, "77": {"win_rate": 0.529, "games": 51}, "80": {"win_rate": 0.598, "games": 174}, "66": {"win_rate": 0.526, "games": 38}, "78": {"win_rate": 0.548, "games": 93}, "52": {"win_rate": 0.521, "games": 165}, "131": {"win_rate": 0.519, "games": 237}, "51": {"win_rate": 0.506, "games": 156}, "107": {"win_rate": 0.535, "games": 217}, "94": {"win_rate": 0.545, "games": 341}, "98": {"win_rate": 0.472, "games": 142}, "53": {"win_rate": 0.462, "games": 418}, "13": {"win_rate": 0.504, "games": 252}, "6": {"win_rate": 0.529, "games": 792}, "7": {"win_rate": 0.518, "games": 760}, "19": {"win_rate": 0.478, "games": 391}, "112": {"win_rate": 0.517, "games": 230}, "60": {"win_rate": 0.535, "games": 426}, "17": {"win_rate": 0.483, "games": 402}, "62": {"win_rate": 0.517, "games": 271}, "43": {"win_rate": 0.498, "games": 243}, "21": {"win_rate": 0.491, "games": 585}, "81": {"win_rate": 0.517, "games": 203}, "87": {"win_rate": 0.508, "games": 425}, "3": {"win_rate": 0.519, "games": 160}, "28": {"win_rate": 0.526, "games": 424}, "72": {"win_rate": 0.449, "games": 216}, "110": {"win_rate": 0.538, "games": 476}, "57": {"win_rate": 0.503, "games": 159}, "88": {"win_rate": 0.524, "games": 330}, "63": {"win_rate": 0.476, "games": 550}, "64": {"win_rate": 0.476, "games": 647}, "137": {"win_rate": 0.518, "games": 247}, "42": {"win_rate": 0.548, "games": 843}, "10": {"win_rate": 0.487, "games": 357}, "69": {"win_rate": 0.465, "games": 434}, "37": {"win_rate": 0.51, "games": 559}, "8": {"win_rate": 0.522, "games": 929}, "54": {"win_rate": 0.531, "games": 1016}, "100": {"win_rate": 0.486, "games": 393}, "109": {"win_rate": 0.498, "games": 231}, "93": {"win_rate": 0.503, "games": 1228}, "41": {"win_rate": 0.502, "games": 660}, "26": {"win_rate": 0.498, "games": 1722}, "128": {"win_rate": 0.479, "games": 340}, "126": {"win_rate": 0.506, "games": 336}, "5": {"win_rate": 0.511, "games": 713}, "27": {"win_rate": 0.523, "games": 1033}, "114": {"win_rate": 0.46, "games": 541}, "73": {"win_rate": 0.508, "games": 851}, "99": {"win_rate": 0.497, "games": 559}, "123": {"win_rate": 0.486, "games": 627}, "38": {"win_rate": 0.475, "games": 543}, "91": {"win_rate": 0.519, "games": 289}, "14": {"win_rate": 0.499, "games": 1688}, "50": {"win_rate": 0.51, "games": 343}, "71": {"win_rate": 0.5, "games": 1171}, "40": {"win_rate": 0.48, "games": 806}, "46": {"win_rate": 0.458, "games": 419}, "68": {"win_rate": 0.489, "games": 397}, "2": {"win_rate": 0.518, "games": 913}, "92": {"win_rate": 0.54, "games": 113}, "12": {"win_rate": 0.536, "games": 784}, "22": {"win_rate": 0.501, "games": 895}, "30": {"win_rate": 0.504, "games": 1131}, "75": {"win_rate": 0.499, "games": 689}, "48": {"win_rate": 0.504, "games": 567}, "119": {"win_rate": 0.47, "games": 268}, "1": {"win_rate": 0.469, "games": 974}, "67": {"win_rate": 0.532, "games": 744}, "29": {"win_rate": 0.514, "games": 803}, "96": {"win_rate": 0.472, "games": 218}, "61": {"win_rate": 0.498, "games": 241}, "121": {"win_rate": 0.506, "games": 318}, "39": {"win_rate": 0.472, "games": 803}, "20": {"win_rate": 0.515, "games": 505}, "79": {"win_rate": 0.449, "games": 158}, "86": {"win_rate": 0.489, "games": 1320}, "47": {"win_rate": 0.479, "games": 363}, "101": {"win_rate": 0.48, "games": 737}, "135": {"win_rate": 0.517, "games": 441}, "145": {"win_rate": 0.471, "games": 257}, "44": {"win_rate": 0.488, "games": 1040}, "105": {"win_rate": 0.511, "games": 716}, "11": {"win_rate": 0.463, "games": 864}, "84": {"win_rate": 0.495, "games": 1050}, "120": {"win_rate": 0.473, "games": 484}, "56": {"win_rate": 0.497, "games": 328}, "85": {"win_rate": 0.502, "games": 542}, "55": {"win_rate": 0.474, "games": 95}, "31": {"win_rate": 0.497, "games": 723}, "35": {"win_rate": 0.479, "games": 1086}, "15": {"win_rate": 0.477, "games": 264}, "70": {"win_rate": 0.45, "games": 593}, "4": {"win_rate": 0.5, "games": 272}, "74": {"win_rate": 0.502, "games": 1212}, "108": {"win_rate": 0.492, "games": 252}, "76": {"win_rate": 0.462, "games": 273}, "58": {"win_rate": 0.459, "games": 122}, "18": {"win_rate": 0.469, "games": 303}, "90": {"win_rate": 0.492, "games": 325}, "25": {"win_rate": 0.455, "games": 723}, "9": {"win_rate": 0.47, "games": 396}, "32": {"win_rate": 0.494, "games": 326}, "36": {"win_rate": 0.488, "games": 769}, "136": {"win_rate": 0.459, "games": 255}, "97": {"win_rate": 0.452, "games": 629}, "23": {"win_rate": 0.466, "games": 247}, "89": {"win_rate": 0.471, "games": 172}, "16": {"win_rate": 0.461, "games": 345}, "138": {"win_rate": 0.452, "games": 416}, "106": {"win_rate": 0.448, "games": 422}, "34": {"win_rate": 0.402, "games": 194}, "49": {"win_rate": 0.443, "games": 262}, "111": {"win_rate": 0.444, "games": 243}, "113": {"win_rate": 0.462, "games": 266}, "104": {"win_rate": 0.473, "games": 865}, "33": {"win_rate": 0.444, "games": 160}, "129": {"win_rate": 0.384, "games": 417}, "45": {"win_rate": 0.447, "games": 219}, "82": {"win_rate": 0.443, "games": 174}, "102": {"win_rate": 0.415, "games": 171}, "95": {"win_rate": 0.395, "games": 124}}}, "HERALD_GUARDIAN": {"vs": {"79": {"win_rate": 0.632, "games": 95}, "100": {"win_rate": 0.59, "games": 156}, "138": {"win_rate": 0.555, "games": 220}, "69": {"win_rate": 0.592, "games": 228}, "68": {"win_rate": 0.541, "games": 307}, "145": {"win_rate": 0.57, "games": 142}, "37": {"win_rate": 0.532, "games": 391}, "70": {"win_rate": 0.579, "games": 309}, "76": {"win_rate": 0.555, "games": 173}, "98": {"win_rate": 0.589, "games": 107}, "88": {"win_rate": 0.506, "games": 237}, "57": {"win_rate": 0.538, "games": 104}, "85": {"win_rate": 0.505, "games": 473}, "38": {"win_rate": 0.542, "games": 389}, "60": {"win_rate": 0.522, "games": 245}, "67": {"win_rate": 0.462, "games": 480}, "4": {"win_rate": 0.496, "games": 234}, "63": {"win_rate": 0.551, "games": 392}, "13": {"win_rate": 0.564, "games": 165}, "94": {"win_rate": 0.497, "games": 181}, "30": {"win_rate": 0.497, "games": 888}, "51": {"win_rate": 0.543, "games": 105}, "120": {"win_rate": 0.536, "games": 207}, "32": {"win_rate": 0.489, "games": 327}, "129": {"win_rate": 0.563, "games": 268}, "97": {"win_rate": 0.533, "games": 330}, "78": {"win_rate": 0.5, "games": 58}, "136": {"win_rate": 0.524, "games": 206}, "123": {"win_rate": 0.516, "games": 473}, "86": {"win_rate": 0.516, "games": 760}, "58": {"win_rate": 0.519, "games": 135}, "17": {"win_rate": 0.54, "games": 300}, "114": {"win_rate": 0.546, "games": 350}, "36": {"win_rate": 0.475, "games": 691}, "56": {"win_rate": 0.497, "games": 306}, "55": {"win_rate": 0.515, "games": 68}, "1": {"win_rate": 0.519, "games": 659}, "64": {"win_rate": 0.52, "games": 458}, "42": {"win_rate": 0.444, "games": 674}, "126": {"win_rate": 0.5, "games": 216}, "61": {"win_rate": 0.49, "games": 247}, "52": {"win_rate": 0.504, "games": 135}, "44": {"win_rate": 0.485, "games": 743}, "41": {"win_rate": 0.499, "games": 439}, "22": {"win_rate": 0.48, "games": 696}, "23": {"win_rate": 0.51, "games": 202}, "54": {"win_rate": 0.475, "games": 505}, "119": {"win_rate": 0.528, "games": 193}, "99": {"win_rate": 0.466, "games": 479}, "19": {"win_rate": 0.544, "games": 239}, "82": {"win_rate": 0.483, "games": 145}, "84": {"win_rate": 0.471, "games": 851}, "27": {"win_rate": 0.47, "games": 791}, "80": {"win_rate": 0.468, "games": 126}, "109": {"win_rate": 0.511, "games": 131}, "74": {"win_rate": 0.472, "games": 870}, "18": {"win_rate": 0.496, "games": 230}, "26": {"win_rate": 0.496, "games": 1338}, "50": {"win_rate": 0.49, "games": 239}, "14": {"win_rate": 0.483, "games": 1344}, "73": {"win_rate": 0.471, "games": 456}, "107": {"win_rate": 0.509, "games": 110}, "29": {"win_rate": 0.459, "games": 588}, "47": {"win_rate": 0.505, "games": 428}, "15": {"win_rate": 0.489, "games": 272}, "6": {"win_rate": 0.493, "games": 582}, "137": {"win_rate": 0.472, "games": 197}, "71": {"win_rate": 0.472, "games": 777}, "46": {"win_rate": 0.52, "games": 271}, "2": {"win_rate": 0.447, "games": 804}, "10": {"win_rate": 0.502, "games": 227}, "128": {"win_rate": 0.502, "games": 211}, "110": {"win_rate": 0.458, "games": 286}, "35": {"win_rate": 0.471, "games": 1006}, "12": {"win_rate": 0.445, "games": 517}, "93": {"win_rate": 0.474, "games": 646}, "75": {"win_rate": 0.459, "games": 503}, "31": {"win_rate": 0.454, "games": 542}, "53": {"win_rate": 0.531, "games": 407}, "11": {"win_rate": 0.492, "games": 618}, "8": {"win_rate": 0.459, "games": 599}, "105": {"win_rate": 0.447, "games": 588}, "25": {"win_rate": 0.498, "games": 608}, "40": {"win_rate": 0.488, "games": 607}, "101": {"win_rate": 0.475, "games": 608}, "20": {"win_rate": 0.439, "games": 328}, "91": {"win_rate": 0.45, "games": 180}, "21": {"win_rate": 0.502, "games": 524}, "3": {"win_rate": 0.471, "games": 102}, "106": {"win_rate": 0.482, "games": 224}, "43": {"win_rate": 0.489, "games": 219}, "87": {"win_rate": 0.481, "games": 243}, "104": {"win_rate": 0.434, "games": 774}, "28": {"win_rate": 0.461, "games": 393}, "5": {"win_rate": 0.436, "games": 621}, "48": {"win_rate": 0.448, "games": 344}, "39": {"win_rate": 0.486, "games": 560}, "7": {"win_rate": 0.47, "games": 626}, "103": {"win_rate": 0.446, "games": 56}, "131": {"win_rate": 0.48, "games": 100}, "45": {"win_rate": 0.466, "games": 191}, "121": {"win_rate": 0.441, "games": 188}, "49": {"win_rate": 0.462, "games": 234}, "59": {"win_rate": 0.488, "games": 299}, "72": {"win_rate": 0.533, "games": 105}, "81": {"win_rate": 0.453, "games": 223}, "83": {"win_rate": 0.46, "games": 100}, "113": {"win_rate": 0.445, "games": 218}, "111": {"win_rate": 0.469, "games": 128}, "89": {"win_rate": 0.444, "games": 169}, "90": {"win_rate": 0.46, "games": 237}, "33": {"win_rate": 0.451, "games": 144}, "96": {"win_rate": 0.455, "games": 191}, "108": {"win_rate": 0.431, "games": 167}, "9": {"win_rate": 0.44, "games": 284}, "135": {"win_rate": 0.417, "games": 290}, "62": {"win_rate": 0.443, "games": 183}, "16": {"win_rate": 0.43, "games": 298}, "102": {"win_rate": 0.424, "games": 125}, "34": {"win_rate": 0.497, "games": 143}, "95": {"win_rate": 0.414, "games": 128}, "112": {"win_rate": 0.422, "games": 166}, "92": {"win_rate": 0.388, "games": 103}, "77": {"win_rate": 0.446, "games": 56}, "155": {"win_rate": 0.395, "games": 81}, "66": {"win_rate": 0.344, "games": 32}}, "with": {"66": {"win_rate": 0.611, "games": 18}, "77": {"win_rate": 0.565, "games": 46}, "52": {"win_rate": 0.6, "games": 100}, "155": {"win_rate": 0.554, "games": 56}, "83": {"win_rate": 0.568, "games": 95}, "119": {"win_rate": 0.521, "games": 142}, "78": {"win_rate": 0.558, "games": 52}, "92": {"win_rate": 0.554, "games": 74}, "51": {"win_rate": 0.507, "games": 67}, "25": {"win_rate": 0.501, "games": 433}, "120": {"win_rate": 0.502, "games": 213}, "5": {"win_rate": 0.55, "games": 469}, "13": {"win_rate": 0.479, "games": 117}, "53": {"win_rate": 0.469, "games": 271}, "19": {"win_rate": 0.474, "games": 209}, "4": {"win_rate": 0.545, "games": 213}, "16": {"win_rate": 0.532, "games": 218}, "85": {"win_rate": 0.537, "games": 326}, "136": {"win_rate": 0.503, "games": 163}, "128": {"win_rate": 0.494, "games": 162}, "54": {"win_rate": 0.535, "games": 469}, "33": {"win_rate": 0.513, "games": 117}, "6": {"win_rate": 0.505, "games": 527}, "55": {"win_rate": 0.5, "games": 62}, "82": {"win_rate": 0.52, "games": 125}, "106": {"win_rate": 0.493, "games": 207}, "10": {"win_rate": 0.487, "games": 191}, "67": {"win_rate": 0.565, "games": 483}, "27": {"win_rate": 0.529, "games": 647}, "88": {"win_rate": 0.526, "games": 209}, "100": {"win_rate": 0.469, "games": 175}, "29": {"win_rate": 0.533, "games": 430}, "98": {"win_rate": 0.444, "games": 81}, "30": {"win_rate": 0.522, "games": 692}, "40": {"win_rate": 0.486, "games": 403}, "8": {"win_rate": 0.517, "games": 606}, "95": {"win_rate": 0.518, "games": 114}, "121": {"win_rate": 0.521, "games": 163}, "107": {"win_rate": 0.481, "games": 79}, "111": {"win_rate": 0.487, "games": 117}, "50": {"win_rate": 0.5, "games": 200}, "1": {"win_rate": 0.483, "games": 619}, "14": {"win_rate": 0.506, "games": 1042}, "46": {"win_rate": 0.461, "games": 245}, "70": {"win_rate": 0.46, "games": 309}, "12": {"win_rate": 0.53, "games": 508}, "57": {"win_rate": 0.485, "games": 101}, "31": {"win_rate": 0.519, "games": 391}, "21": {"win_rate": 0.464, "games": 399}, "17": {"win_rate": 0.463, "games": 218}, "104": {"win_rate": 0.526, "games": 626}, "138": {"win_rate": 0.489, "games": 219}, "105": {"win_rate": 0.518, "games": 413}, "43": {"win_rate": 0.469, "games": 162}, "42": {"win_rate": 0.549, "games": 494}, "64": {"win_rate": 0.474, "games": 323}, "101": {"win_rate": 0.485, "games": 429}, "86": {"win_rate": 0.481, "games": 557}, "9": {"win_rate": 0.5, "games": 218}, "59": {"win_rate": 0.462, "games": 236}, "36": {"win_rate": 0.518, "games": 512}, "18": {"win_rate": 0.484, "games": 248}, "102": {"win_rate": 0.5, "games": 84}, "84": {"win_rate": 0.509, "games": 664}, "11": {"win_rate": 0.471, "games": 522}, "87": {"win_rate": 0.471, "games": 204}, "109": {"win_rate": 0.468, "games": 173}, "103": {"win_rate": 0.5, "games": 32}, "93": {"win_rate": 0.488, "games": 584}, "113": {"win_rate": 0.495, "games": 182}, "80": {"win_rate": 0.506, "games": 87}, "48": {"win_rate": 0.495, "games": 313}, "41": {"win_rate": 0.479, "games": 445}, "35": {"win_rate": 0.487, "games": 747}, "28": {"win_rate": 0.48, "games": 281}, "131": {"win_rate": 0.46, "games": 87}, "75": {"win_rate": 0.495, "games": 386}, "73": {"win_rate": 0.495, "games": 372}, "58": {"win_rate": 0.462, "games": 104}, "114": {"win_rate": 0.433, "games": 321}, "108": {"win_rate": 0.492, "games": 130}, "112": {"win_rate": 0.464, "games": 125}, "23": {"win_rate": 0.457, "games": 138}, "99": {"win_rate": 0.498, "games": 450}, "2": {"win_rate": 0.503, "games": 612}, "94": {"win_rate": 0.489, "games": 174}, "110": {"win_rate": 0.488, "games": 201}, "15": {"win_rate": 0.466, "games": 223}, "47": {"win_rate": 0.45, "games": 298}, "49": {"win_rate": 0.465, "games": 202}, "145": {"win_rate": 0.442, "games": 129}, "37": {"win_rate": 0.477, "games": 256}, "126": {"win_rate": 0.468, "games": 156}, "74": {"win_rate": 0.485, "games": 596}, "26": {"win_rate": 0.461, "games": 965}, "72": {"win_rate": 0.391, "games": 87}, "62": {"win_rate": 0.463, "games": 134}, "44": {"win_rate": 0.475, "games": 676}, "81": {"win_rate": 0.462, "games": 171}, "38": {"win_rate": 0.437, "games": 364}, "71": {"win_rate": 0.466, "games": 607}, "20": {"win_rate": 0.484, "games": 246}, "79": {"win_rate": 0.4, "games": 60}, "63": {"win_rate": 0.421, "games": 361}, "61": {"win_rate": 0.463, "games": 188}, "3": {"win_rate": 0.449, "games": 78}, "69": {"win_rate": 0.409, "games": 208}, "60": {"win_rate": 0.446, "games": 193}, "89": {"win_rate": 0.457, "games": 162}, "7": {"win_rate": 0.438, "games": 486}, "56": {"win_rate": 0.451, "games": 257}, "97": {"win_rate": 0.42, "games": 264}, "34": {"win_rate": 0.377, "games": 146}, "39": {"win_rate": 0.413, "games": 412}, "135": {"win_rate": 0.465, "games": 198}, "76": {"win_rate": 0.411, "games": 141}, "91": {"win_rate": 0.446, "games": 148}, "96": {"win_rate": 0.423, "games": 149}, "123": {"win_rate": 0.415, "games": 340}, "32": {"win_rate": 0.445, "games": 272}, "22": {"win_rate": 0.436, "games": 484}, "45": {"win_rate": 0.414, "games": 140}, "129": {"win_rate": 0.365, "games": 181}, "137": {"win_rate": 0.426, "games": 148}, "90": {"win_rate": 0.402, "games": 179}, "68": {"win_rate": 0.409, "games": 215}}}}