{"DIVINE_IMMORTAL": {"vs": {"3": {"win_rate": 0.569, "games": 295}, "34": {"win_rate": 0.623, "games": 204}, "58": {"win_rate": 0.57, "games": 158}, "88": {"win_rate": 0.536, "games": 552}, "43": {"win_rate": 0.557, "games": 395}, "51": {"win_rate": 0.53, "games": 217}, "121": {"win_rate": 0.512, "games": 375}, "87": {"win_rate": 0.538, "games": 800}, "17": {"win_rate": 0.56, "games": 455}, "66": {"win_rate": 0.545, "games": 22}, "7": {"win_rate": 0.531, "games": 827}, "135": {"win_rate": 0.498, "games": 660}, "128": {"win_rate": 0.545, "games": 455}, "90": {"win_rate": 0.502, "games": 416}, "53": {"win_rate": 0.561, "games": 380}, "109": {"win_rate": 0.494, "games": 257}, "18": {"win_rate": 0.526, "games": 213}, "137": {"win_rate": 0.511, "games": 425}, "85": {"win_rate": 0.496, "games": 560}, "25": {"win_rate": 0.529, "games": 857}, "96": {"win_rate": 0.559, "games": 311}, "63": {"win_rate": 0.545, "games": 627}, "44": {"win_rate": 0.529, "games": 737}, "5": {"win_rate": 0.52, "games": 852}, "13": {"win_rate": 0.53, "games": 385}, "97": {"win_rate": 0.53, "games": 880}, "50": {"win_rate": 0.504, "games": 228}, "49": {"win_rate": 0.539, "games": 230}, "8": {"win_rate": 0.504, "games": 790}, "54": {"win_rate": 0.49, "games": 917}, "31": {"win_rate": 0.51, "games": 978}, "86": {"win_rate": 0.503, "games": 2180}, "120": {"win_rate": 0.518, "games": 1058}, "68": {"win_rate": 0.535, "games": 400}, "56": {"win_rate": 0.485, "games": 344}, "98": {"win_rate": 0.573, "games": 227}, "70": {"win_rate": 0.529, "games": 478}, "84": {"win_rate": 0.512, "games": 764}, "106": {"win_rate": 0.509, "games": 727}, "36": {"win_rate": 0.512, "games": 848}, "89": {"win_rate": 0.504, "games": 129}, "131": {"win_rate": 0.515, "games": 429}, "94": {"win_rate": 0.504, "games": 270}, "129": {"win_rate": 0.561, "games": 766}, "138": {"win_rate": 0.518, "games": 490}, "123": {"win_rate": 0.512, "games": 725}, "42": {"win_rate": 0.495, "games": 705}, "136": {"win_rate": 0.513, "games": 310}, "29": {"win_rate": 0.492, "games": 1395}, "4": {"win_rate": 0.485, "games": 200}, "126": {"win_rate": 0.514, "games": 843}, "69": {"win_rate": 0.529, "games": 754}, "60": {"win_rate": 0.474, "games": 768}, "46": {"win_rate": 0.558, "games": 360}, "76": {"win_rate": 0.516, "games": 283}, "92": {"win_rate": 0.424, "games": 151}, "78": {"win_rate": 0.473, "games": 165}, "6": {"win_rate": 0.491, "games": 674}, "99": {"win_rate": 0.52, "games": 527}, "67": {"win_rate": 0.49, "games": 439}, "105": {"win_rate": 0.473, "games": 725}, "52": {"win_rate": 0.497, "games": 318}, "16": {"win_rate": 0.534, "games": 491}, "110": {"win_rate": 0.466, "games": 869}, "101": {"win_rate": 0.521, "games": 948}, "2": {"win_rate": 0.483, "games": 1005}, "28": {"win_rate": 0.485, "games": 745}, "100": {"win_rate": 0.499, "games": 676}, "119": {"win_rate": 0.504, "games": 397}, "27": {"win_rate": 0.469, "games": 1236}, "30": {"win_rate": 0.508, "games": 1013}, "26": {"win_rate": 0.501, "games": 2072}, "14": {"win_rate": 0.496, "games": 1913}, "74": {"win_rate": 0.459, "games": 1413}, "112": {"win_rate": 0.455, "games": 376}, "19": {"win_rate": 0.517, "games": 770}, "48": {"win_rate": 0.477, "games": 750}, "21": {"win_rate": 0.49, "games": 635}, "47": {"win_rate": 0.484, "games": 440}, "114": {"win_rate": 0.506, "games": 1051}, "33": {"win_rate": 0.462, "games": 221}, "107": {"win_rate": 0.471, "games": 340}, "73": {"win_rate": 0.485, "games": 1241}, "93": {"win_rate": 0.486, "games": 1293}, "39": {"win_rate": 0.485, "games": 1258}, "55": {"win_rate": 0.485, "games": 134}, "40": {"win_rate": 0.502, "games": 1092}, "111": {"win_rate": 0.472, "games": 326}, "71": {"win_rate": 0.484, "games": 1315}, "22": {"win_rate": 0.479, "games": 1157}, "41": {"win_rate": 0.48, "games": 744}, "9": {"win_rate": 0.482, "games": 421}, "1": {"win_rate": 0.499, "games": 583}, "20": {"win_rate": 0.452, "games": 480}, "65": {"win_rate": 0.452, "games": 471}, "72": {"win_rate": 0.536, "games": 235}, "64": {"win_rate": 0.512, "games": 693}, "82": {"win_rate": 0.46, "games": 189}, "145": {"win_rate": 0.48, "games": 377}, "37": {"win_rate": 0.485, "games": 584}, "38": {"win_rate": 0.472, "games": 708}, "23": {"win_rate": 0.468, "games": 280}, "11": {"win_rate": 0.487, "games": 813}, "104": {"win_rate": 0.449, "games": 985}, "45": {"win_rate": 0.447, "games": 257}, "15": {"win_rate": 0.484, "games": 465}, "108": {"win_rate": 0.471, "games": 497}, "10": {"win_rate": 0.485, "games": 324}, "35": {"win_rate": 0.486, "games": 963}, "102": {"win_rate": 0.448, "games": 248}, "81": {"win_rate": 0.467, "games": 184}, "91": {"win_rate": 0.433, "games": 284}, "59": {"win_rate": 0.434, "games": 463}, "113": {"win_rate": 0.446, "games": 193}, "80": {"win_rate": 0.408, "games": 289}, "79": {"win_rate": 0.475, "games": 295}, "95": {"win_rate": 0.462, "games": 104}, "62": {"win_rate": 0.42, "games": 333}, "57": {"win_rate": 0.439, "games": 187}, "12": {"win_rate": 0.405, "games": 605}, "77": {"win_rate": 0.437, "games": 103}, "32": {"win_rate": 0.416, "games": 303}, "83": {"win_rate": 0.398, "games": 201}, "155": {"win_rate": 0.423, "games": 156}, "61": {"win_rate": 0.411, "games": 129}, "103": {"win_rate": 0.333, "games": 87}}, "with": {"57": {"win_rate": 0.59, "games": 134}, "103": {"win_rate": 0.603, "games": 63}, "131": {"win_rate": 0.56, "games": 200}, "4": {"win_rate": 0.579, "games": 266}, "51": {"win_rate": 0.562, "games": 178}, "3": {"win_rate": 0.574, "games": 115}, "50": {"win_rate": 0.566, "games": 122}, "18": {"win_rate": 0.55, "games": 191}, "32": {"win_rate": 0.569, "games": 262}, "52": {"win_rate": 0.548, "games": 283}, "62": {"win_rate": 0.569, "games": 188}, "20": {"win_rate": 0.564, "games": 335}, "98": {"win_rate": 0.483, "games": 265}, "95": {"win_rate": 0.524, "games": 82}, "102": {"win_rate": 0.549, "games": 144}, "93": {"win_rate": 0.536, "games": 1302}, "26": {"win_rate": 0.526, "games": 1215}, "105": {"win_rate": 0.558, "games": 400}, "15": {"win_rate": 0.514, "games": 430}, "45": {"win_rate": 0.549, "games": 142}, "111": {"win_rate": 0.54, "games": 124}, "7": {"win_rate": 0.531, "games": 735}, "55": {"win_rate": 0.528, "games": 125}, "14": {"win_rate": 0.522, "games": 1619}, "72": {"win_rate": 0.464, "games": 224}, "113": {"win_rate": 0.529, "games": 136}, "90": {"win_rate": 0.551, "games": 332}, "71": {"win_rate": 0.522, "games": 1111}, "2": {"win_rate": 0.535, "games": 970}, "106": {"win_rate": 0.523, "games": 738}, "44": {"win_rate": 0.511, "games": 702}, "89": {"win_rate": 0.525, "games": 118}, "17": {"win_rate": 0.494, "games": 569}, "114": {"win_rate": 0.499, "games": 908}, "120": {"win_rate": 0.515, "games": 983}, "31": {"win_rate": 0.523, "games": 512}, "70": {"win_rate": 0.5, "games": 520}, "137": {"win_rate": 0.529, "games": 414}, "104": {"win_rate": 0.531, "games": 791}, "38": {"win_rate": 0.509, "games": 595}, "39": {"win_rate": 0.509, "games": 1238}, "123": {"win_rate": 0.5, "games": 396}, "107": {"win_rate": 0.521, "games": 263}, "135": {"win_rate": 0.538, "games": 809}, "91": {"win_rate": 0.525, "games": 162}, "73": {"win_rate": 0.505, "games": 1254}, "1": {"win_rate": 0.479, "games": 509}, "36": {"win_rate": 0.501, "games": 757}, "74": {"win_rate": 0.533, "games": 1245}, "53": {"win_rate": 0.466, "games": 268}, "21": {"win_rate": 0.498, "games": 510}, "82": {"win_rate": 0.51, "games": 200}, "56": {"win_rate": 0.528, "games": 337}, "11": {"win_rate": 0.479, "games": 814}, "65": {"win_rate": 0.518, "games": 390}, "37": {"win_rate": 0.482, "games": 245}, "10": {"win_rate": 0.476, "games": 315}, "110": {"win_rate": 0.527, "games": 554}, "78": {"win_rate": 0.523, "games": 172}, "84": {"win_rate": 0.494, "games": 530}, "83": {"win_rate": 0.519, "games": 135}, "136": {"win_rate": 0.485, "games": 268}, "43": {"win_rate": 0.49, "games": 294}, "19": {"win_rate": 0.467, "games": 713}, "22": {"win_rate": 0.496, "games": 706}, "35": {"win_rate": 0.471, "games": 726}, "34": {"win_rate": 0.441, "games": 177}, "88": {"win_rate": 0.513, "games": 429}, "27": {"win_rate": 0.515, "games": 656}, "77": {"win_rate": 0.494, "games": 87}, "16": {"win_rate": 0.455, "games": 486}, "109": {"win_rate": 0.52, "games": 223}, "97": {"win_rate": 0.478, "games": 801}, "68": {"win_rate": 0.469, "games": 175}, "28": {"win_rate": 0.5, "games": 688}, "61": {"win_rate": 0.488, "games": 121}, "76": {"win_rate": 0.475, "games": 284}, "48": {"win_rate": 0.497, "games": 614}, "94": {"win_rate": 0.489, "games": 235}, "9": {"win_rate": 0.484, "games": 277}, "81": {"win_rate": 0.475, "games": 198}, "23": {"win_rate": 0.485, "games": 262}, "145": {"win_rate": 0.474, "games": 371}, "29": {"win_rate": 0.495, "games": 1252}, "85": {"win_rate": 0.51, "games": 398}, "49": {"win_rate": 0.462, "games": 184}, "12": {"win_rate": 0.518, "games": 531}, "54": {"win_rate": 0.506, "games": 1030}, "96": {"win_rate": 0.443, "games": 280}, "60": {"win_rate": 0.508, "games": 691}, "8": {"win_rate": 0.492, "games": 828}, "112": {"win_rate": 0.514, "games": 218}, "41": {"win_rate": 0.479, "games": 781}, "128": {"win_rate": 0.462, "games": 303}, "80": {"win_rate": 0.516, "games": 254}, "126": {"win_rate": 0.465, "games": 782}, "69": {"win_rate": 0.45, "games": 715}, "79": {"win_rate": 0.448, "games": 116}, "100": {"win_rate": 0.471, "games": 495}, "13": {"win_rate": 0.464, "games": 457}, "59": {"win_rate": 0.492, "games": 327}, "86": {"win_rate": 0.485, "games": 1220}, "129": {"win_rate": 0.419, "games": 735}, "42": {"win_rate": 0.482, "games": 705}, "67": {"win_rate": 0.481, "games": 447}, "40": {"win_rate": 0.452, "games": 504}, "6": {"win_rate": 0.478, "games": 596}, "33": {"win_rate": 0.49, "games": 151}, "63": {"win_rate": 0.442, "games": 570}, "119": {"win_rate": 0.454, "games": 249}, "92": {"win_rate": 0.538, "games": 132}, "25": {"win_rate": 0.455, "games": 701}, "30": {"win_rate": 0.446, "games": 464}, "87": {"win_rate": 0.458, "games": 349}, "46": {"win_rate": 0.404, "games": 292}, "121": {"win_rate": 0.482, "games": 193}, "5": {"win_rate": 0.455, "games": 411}, "99": {"win_rate": 0.434, "games": 477}, "155": {"win_rate": 0.45, "games": 111}, "64": {"win_rate": 0.406, "games": 401}, "58": {"win_rate": 0.43, "games": 79}, "138": {"win_rate": 0.428, "games": 488}, "47": {"win_rate": 0.439, "games": 371}, "101": {"win_rate": 0.408, "games": 476}, "108": {"win_rate": 0.416, "games": 430}, "66": {"win_rate": 0.4, "games": 25}}}, "LEGEND_ANCIENT": {"vs": {"135": {"win_rate": 0.521, "games": 1320}, "95": {"win_rate": 0.547, "games": 254}, "98": {"win_rate": 0.608, "games": 500}, "33": {"win_rate": 0.53, "games": 613}, "131": {"win_rate": 0.551, "games": 719}, "34": {"win_rate": 0.59, "games": 400}, "17": {"win_rate": 0.567, "games": 1113}, "54": {"win_rate": 0.5, "games": 2286}, "138": {"win_rate": 0.536, "games": 1095}, "36": {"win_rate": 0.51, "games": 2314}, "88": {"win_rate": 0.511, "games": 1269}, "78": {"win_rate": 0.505, "games": 285}, "121": {"win_rate": 0.502, "games": 864}, "50": {"win_rate": 0.507, "games": 604}, "39": {"win_rate": 0.528, "games": 3040}, "120": {"win_rate": 0.523, "games": 1757}, "137": {"win_rate": 0.509, "games": 731}, "112": {"win_rate": 0.502, "games": 637}, "43": {"win_rate": 0.529, "games": 860}, "52": {"win_rate": 0.53, "games": 610}, "27": {"win_rate": 0.496, "games": 2937}, "7": {"win_rate": 0.509, "games": 2219}, "31": {"win_rate": 0.502, "games": 2383}, "44": {"win_rate": 0.523, "games": 1977}, "64": {"win_rate": 0.549, "games": 1860}, "28": {"win_rate": 0.502, "games": 1770}, "106": {"win_rate": 0.518, "games": 1511}, "41": {"win_rate": 0.506, "games": 1841}, "70": {"win_rate": 0.531, "games": 1199}, "67": {"win_rate": 0.478, "games": 1645}, "86": {"win_rate": 0.499, "games": 4775}, "114": {"win_rate": 0.535, "games": 1967}, "51": {"win_rate": 0.528, "games": 475}, "82": {"win_rate": 0.495, "games": 410}, "45": {"win_rate": 0.498, "games": 675}, "110": {"win_rate": 0.475, "games": 1504}, "101": {"win_rate": 0.52, "games": 2296}, "100": {"win_rate": 0.52, "games": 1329}, "155": {"win_rate": 0.527, "games": 300}, "30": {"win_rate": 0.502, "games": 3100}, "76": {"win_rate": 0.518, "games": 751}, "129": {"win_rate": 0.558, "games": 1521}, "128": {"win_rate": 0.53, "games": 1040}, "99": {"win_rate": 0.511, "games": 1196}, "16": {"win_rate": 0.518, "games": 1189}, "2": {"win_rate": 0.481, "games": 2643}, "19": {"win_rate": 0.548, "games": 1421}, "20": {"win_rate": 0.471, "games": 1274}, "56": {"win_rate": 0.471, "games": 729}, "23": {"win_rate": 0.504, "games": 851}, "65": {"win_rate": 0.492, "games": 650}, "8": {"win_rate": 0.483, "games": 2501}, "73": {"win_rate": 0.492, "games": 2661}, "9": {"win_rate": 0.502, "games": 1212}, "96": {"win_rate": 0.53, "games": 855}, "81": {"win_rate": 0.507, "games": 487}, "97": {"win_rate": 0.506, "games": 2214}, "26": {"win_rate": 0.503, "games": 5211}, "22": {"win_rate": 0.495, "games": 2843}, "103": {"win_rate": 0.469, "games": 143}, "46": {"win_rate": 0.531, "games": 816}, "74": {"win_rate": 0.461, "games": 3567}, "10": {"win_rate": 0.52, "games": 662}, "58": {"win_rate": 0.516, "games": 289}, "5": {"win_rate": 0.489, "games": 2184}, "13": {"win_rate": 0.523, "games": 755}, "35": {"win_rate": 0.502, "games": 3088}, "53": {"win_rate": 0.548, "games": 1102}, "14": {"win_rate": 0.496, "games": 4389}, "69": {"win_rate": 0.53, "games": 1580}, "108": {"win_rate": 0.491, "games": 1148}, "63": {"win_rate": 0.525, "games": 1538}, "105": {"win_rate": 0.474, "games": 1680}, "91": {"win_rate": 0.481, "games": 470}, "47": {"win_rate": 0.495, "games": 1207}, "25": {"win_rate": 0.503, "games": 2212}, "57": {"win_rate": 0.503, "games": 431}, "79": {"win_rate": 0.536, "games": 509}, "60": {"win_rate": 0.464, "games": 1611}, "84": {"win_rate": 0.484, "games": 2607}, "62": {"win_rate": 0.465, "games": 699}, "42": {"win_rate": 0.455, "games": 2286}, "87": {"win_rate": 0.493, "games": 1762}, "37": {"win_rate": 0.488, "games": 1376}, "59": {"win_rate": 0.487, "games": 950}, "71": {"win_rate": 0.485, "games": 3228}, "83": {"win_rate": 0.478, "games": 362}, "40": {"win_rate": 0.502, "games": 2723}, "126": {"win_rate": 0.482, "games": 1513}, "68": {"win_rate": 0.5, "games": 1108}, "11": {"win_rate": 0.499, "games": 2200}, "18": {"win_rate": 0.481, "games": 547}, "55": {"win_rate": 0.477, "games": 258}, "3": {"win_rate": 0.462, "games": 485}, "6": {"win_rate": 0.476, "games": 1889}, "123": {"win_rate": 0.487, "games": 1637}, "15": {"win_rate": 0.488, "games": 1180}, "66": {"win_rate": 0.507, "games": 75}, "49": {"win_rate": 0.493, "games": 706}, "102": {"win_rate": 0.472, "games": 599}, "93": {"win_rate": 0.479, "games": 3089}, "90": {"win_rate": 0.454, "games": 782}, "104": {"win_rate": 0.451, "games": 2822}, "21": {"win_rate": 0.491, "games": 1810}, "92": {"win_rate": 0.415, "games": 253}, "1": {"win_rate": 0.492, "games": 1765}, "109": {"win_rate": 0.476, "games": 420}, "107": {"win_rate": 0.457, "games": 689}, "85": {"win_rate": 0.445, "games": 1505}, "48": {"win_rate": 0.46, "games": 1475}, "80": {"win_rate": 0.431, "games": 543}, "4": {"win_rate": 0.447, "games": 589}, "72": {"win_rate": 0.528, "games": 612}, "29": {"win_rate": 0.442, "games": 3000}, "111": {"win_rate": 0.456, "games": 700}, "94": {"win_rate": 0.456, "games": 719}, "145": {"win_rate": 0.481, "games": 765}, "119": {"win_rate": 0.477, "games": 798}, "136": {"win_rate": 0.47, "games": 651}, "32": {"win_rate": 0.436, "games": 706}, "38": {"win_rate": 0.485, "games": 1293}, "12": {"win_rate": 0.417, "games": 1310}, "113": {"win_rate": 0.437, "games": 435}, "89": {"win_rate": 0.429, "games": 280}, "61": {"win_rate": 0.426, "games": 338}, "77": {"win_rate": 0.42, "games": 157}}, "with": {"155": {"win_rate": 0.527, "games": 264}, "82": {"win_rate": 0.559, "games": 399}, "3": {"win_rate": 0.553, "games": 237}, "38": {"win_rate": 0.505, "games": 1197}, "97": {"win_rate": 0.522, "games": 1757}, "112": {"win_rate": 0.542, "games": 367}, "50": {"win_rate": 0.539, "games": 358}, "7": {"win_rate": 0.531, "games": 1768}, "71": {"win_rate": 0.523, "games": 2753}, "41": {"win_rate": 0.524, "games": 1952}, "80": {"win_rate": 0.558, "games": 443}, "51": {"win_rate": 0.499, "games": 411}, "136": {"win_rate": 0.509, "games": 511}, "14": {"win_rate": 0.515, "games": 3733}, "62": {"win_rate": 0.54, "games": 424}, "83": {"win_rate": 0.523, "games": 281}, "34": {"win_rate": 0.463, "games": 408}, "31": {"win_rate": 0.529, "games": 1252}, "58": {"win_rate": 0.494, "games": 168}, "25": {"win_rate": 0.503, "games": 1772}, "4": {"win_rate": 0.536, "games": 576}, "107": {"win_rate": 0.529, "games": 465}, "90": {"win_rate": 0.537, "games": 607}, "12": {"win_rate": 0.551, "games": 1242}, "2": {"win_rate": 0.534, "games": 2820}, "131": {"win_rate": 0.499, "games": 401}, "93": {"win_rate": 0.512, "games": 2918}, "104": {"win_rate": 0.538, "games": 2483}, "91": {"win_rate": 0.522, "games": 291}, "26": {"win_rate": 0.505, "games": 3044}, "105": {"win_rate": 0.528, "games": 1012}, "21": {"win_rate": 0.494, "games": 1317}, "65": {"win_rate": 0.518, "games": 556}, "100": {"win_rate": 0.495, "games": 842}, "52": {"win_rate": 0.496, "games": 514}, "27": {"win_rate": 0.528, "games": 1719}, "36": {"win_rate": 0.521, "games": 2072}, "67": {"win_rate": 0.538, "games": 1594}, "55": {"win_rate": 0.512, "games": 211}, "81": {"win_rate": 0.499, "games": 503}, "45": {"win_rate": 0.516, "games": 372}, "44": {"win_rate": 0.499, "games": 2007}, "33": {"win_rate": 0.516, "games": 343}, "18": {"win_rate": 0.507, "games": 535}, "60": {"win_rate": 0.53, "games": 1505}, "145": {"win_rate": 0.489, "games": 708}, "1": {"win_rate": 0.485, "games": 1642}, "87": {"win_rate": 0.498, "games": 853}, "61": {"win_rate": 0.514, "games": 255}, "74": {"win_rate": 0.538, "games": 2821}, "126": {"win_rate": 0.504, "games": 1293}, "129": {"win_rate": 0.45, "games": 1538}, "120": {"win_rate": 0.499, "games": 1588}, "5": {"win_rate": 0.507, "games": 1173}, "39": {"win_rate": 0.494, "games": 2624}, "92": {"win_rate": 0.557, "games": 201}, "109": {"win_rate": 0.496, "games": 379}, "96": {"win_rate": 0.469, "games": 833}, "42": {"win_rate": 0.531, "games": 2256}, "121": {"win_rate": 0.518, "games": 390}, "123": {"win_rate": 0.491, "games": 960}, "73": {"win_rate": 0.503, "games": 2526}, "43": {"win_rate": 0.483, "games": 687}, "6": {"win_rate": 0.499, "games": 1668}, "46": {"win_rate": 0.46, "games": 797}, "29": {"win_rate": 0.515, "games": 2924}, "137": {"win_rate": 0.501, "games": 758}, "85": {"win_rate": 0.516, "games": 1033}, "23": {"win_rate": 0.487, "games": 718}, "10": {"win_rate": 0.466, "games": 661}, "106": {"win_rate": 0.483, "games": 1438}, "59": {"win_rate": 0.487, "games": 772}, "11": {"win_rate": 0.472, "games": 1973}, "16": {"win_rate": 0.473, "games": 1156}, "32": {"win_rate": 0.511, "games": 661}, "84": {"win_rate": 0.492, "games": 1940}, "37": {"win_rate": 0.485, "games": 794}, "17": {"win_rate": 0.455, "games": 1234}, "8": {"win_rate": 0.504, "games": 2384}, "48": {"win_rate": 0.497, "games": 1307}, "22": {"win_rate": 0.489, "games": 1785}, "110": {"win_rate": 0.518, "games": 997}, "49": {"win_rate": 0.474, "games": 671}, "35": {"win_rate": 0.479, "games": 2309}, "20": {"win_rate": 0.516, "games": 858}, "54": {"win_rate": 0.517, "games": 2536}, "88": {"win_rate": 0.497, "games": 879}, "114": {"win_rate": 0.458, "games": 1711}, "64": {"win_rate": 0.449, "games": 1103}, "135": {"win_rate": 0.514, "games": 1454}, "63": {"win_rate": 0.45, "games": 1338}, "128": {"win_rate": 0.455, "games": 664}, "98": {"win_rate": 0.415, "games": 573}, "95": {"win_rate": 0.482, "games": 276}, "113": {"win_rate": 0.497, "games": 370}, "47": {"win_rate": 0.475, "games": 1002}, "19": {"win_rate": 0.433, "games": 1217}, "69": {"win_rate": 0.441, "games": 1548}, "53": {"win_rate": 0.424, "games": 745}, "57": {"win_rate": 0.464, "games": 330}, "119": {"win_rate": 0.461, "games": 471}, "77": {"win_rate": 0.486, "games": 109}, "30": {"win_rate": 0.476, "games": 1622}, "108": {"win_rate": 0.474, "games": 1099}, "28": {"win_rate": 0.482, "games": 1599}, "138": {"win_rate": 0.46, "games": 1010}, "15": {"win_rate": 0.464, "games": 1020}, "111": {"win_rate": 0.48, "games": 333}, "78": {"win_rate": 0.487, "games": 265}, "86": {"win_rate": 0.478, "games": 2851}, "76": {"win_rate": 0.454, "games": 765}, "94": {"win_rate": 0.476, "games": 657}, "70": {"win_rate": 0.445, "games": 1268}, "99": {"win_rate": 0.458, "games": 1195}, "40": {"win_rate": 0.447, "games": 1497}, "13": {"win_rate": 0.436, "games": 795}, "101": {"win_rate": 0.449, "games": 1250}, "103": {"win_rate": 0.49, "games": 100}, "79": {"win_rate": 0.414, "games": 273}, "72": {"win_rate": 0.4, "games": 458}, "56": {"win_rate": 0.478, "games": 728}, "66": {"win_rate": 0.421, "games": 38}, "89": {"win_rate": 0.45, "games": 200}, "9": {"win_rate": 0.436, "games": 725}, "102": {"win_rate": 0.442, "games": 380}, "68": {"win_rate": 0.408, "games": 593}}}, "CRUSADER_ARCHON": {"vs": {"155": {"win_rate": 0.572, "games": 463}, "128": {"win_rate": 0.576, "games": 1683}, "52": {"win_rate": 0.566, "games": 956}, "57": {"win_rate": 0.554, "games": 757}, "135": {"win_rate": 0.513, "games": 2040}, "110": {"win_rate": 0.516, "games": 2124}, "99": {"win_rate": 0.541, "games": 2758}, "120": {"win_rate": 0.547, "games": 2227}, "98": {"win_rate": 0.595, "games": 798}, "129": {"win_rate": 0.59, "games": 2277}, "33": {"win_rate": 0.534, "games": 1059}, "56": {"win_rate": 0.514, "games": 1442}, "69": {"win_rate": 0.571, "games": 2499}, "95": {"win_rate": 0.524, "games": 557}, "111": {"win_rate": 0.534, "games": 1089}, "106": {"win_rate": 0.54, "games": 2112}, "137": {"win_rate": 0.518, "games": 1095}, "17": {"win_rate": 0.564, "games": 1831}, "27": {"win_rate": 0.503, "games": 5818}, "13": {"win_rate": 0.55, "games": 1209}, "54": {"win_rate": 0.5, "games": 4213}, "34": {"win_rate": 0.58, "games": 777}, "36": {"win_rate": 0.506, "games": 4586}, "45": {"win_rate": 0.516, "games": 1231}, "39": {"win_rate": 0.541, "games": 5077}, "26": {"win_rate": 0.528, "games": 9673}, "44": {"win_rate": 0.52, "games": 4192}, "65": {"win_rate": 0.527, "games": 905}, "20": {"win_rate": 0.494, "games": 2384}, "5": {"win_rate": 0.51, "games": 4256}, "28": {"win_rate": 0.509, "games": 3068}, "138": {"win_rate": 0.53, "games": 1773}, "70": {"win_rate": 0.549, "games": 2036}, "79": {"win_rate": 0.56, "games": 711}, "2": {"win_rate": 0.495, "games": 5286}, "103": {"win_rate": 0.515, "games": 235}, "121": {"win_rate": 0.5, "games": 1435}, "88": {"win_rate": 0.503, "games": 2290}, "14": {"win_rate": 0.513, "games": 8495}, "100": {"win_rate": 0.535, "games": 1738}, "85": {"win_rate": 0.494, "games": 2903}, "63": {"win_rate": 0.55, "games": 2931}, "145": {"win_rate": 0.53, "games": 1092}, "86": {"win_rate": 0.512, "games": 7459}, "41": {"win_rate": 0.514, "games": 3351}, "32": {"win_rate": 0.488, "games": 1639}, "53": {"win_rate": 0.58, "games": 2220}, "58": {"win_rate": 0.526, "games": 530}, "30": {"win_rate": 0.5, "games": 6519}, "4": {"win_rate": 0.488, "games": 1169}, "76": {"win_rate": 0.523, "games": 1577}, "66": {"win_rate": 0.534, "games": 118}, "11": {"win_rate": 0.531, "games": 3874}, "49": {"win_rate": 0.519, "games": 1670}, "50": {"win_rate": 0.495, "games": 1303}, "123": {"win_rate": 0.52, "games": 2577}, "16": {"win_rate": 0.514, "games": 1986}, "62": {"win_rate": 0.509, "games": 1330}, "48": {"win_rate": 0.495, "games": 2516}, "107": {"win_rate": 0.505, "games": 881}, "108": {"win_rate": 0.49, "games": 1891}, "109": {"win_rate": 0.514, "games": 734}, "101": {"win_rate": 0.514, "games": 4485}, "105": {"win_rate": 0.48, "games": 2981}, "37": {"win_rate": 0.502, "games": 2804}, "7": {"win_rate": 0.509, "games": 4165}, "97": {"win_rate": 0.522, "games": 3378}, "22": {"win_rate": 0.498, "games": 5355}, "23": {"win_rate": 0.507, "games": 1504}, "51": {"win_rate": 0.534, "games": 909}, "64": {"win_rate": 0.539, "games": 3742}, "31": {"win_rate": 0.487, "games": 3883}, "19": {"win_rate": 0.547, "games": 2123}, "92": {"win_rate": 0.457, "games": 372}, "114": {"win_rate": 0.543, "games": 2906}, "68": {"win_rate": 0.508, "games": 2200}, "1": {"win_rate": 0.524, "games": 3738}, "25": {"win_rate": 0.519, "games": 4442}, "46": {"win_rate": 0.539, "games": 1490}, "47": {"win_rate": 0.51, "games": 2581}, "59": {"win_rate": 0.509, "games": 1708}, "3": {"win_rate": 0.497, "games": 684}, "73": {"win_rate": 0.491, "games": 4352}, "112": {"win_rate": 0.503, "games": 1158}, "93": {"win_rate": 0.501, "games": 5473}, "83": {"win_rate": 0.507, "games": 681}, "96": {"win_rate": 0.517, "games": 1571}, "74": {"win_rate": 0.474, "games": 6086}, "18": {"win_rate": 0.502, "games": 1254}, "43": {"win_rate": 0.518, "games": 1402}, "60": {"win_rate": 0.482, "games": 2438}, "87": {"win_rate": 0.505, "games": 2708}, "82": {"win_rate": 0.488, "games": 635}, "10": {"win_rate": 0.516, "games": 1093}, "42": {"win_rate": 0.454, "games": 4742}, "8": {"win_rate": 0.479, "games": 5132}, "84": {"win_rate": 0.483, "games": 5973}, "15": {"win_rate": 0.497, "games": 2222}, "119": {"win_rate": 0.515, "games": 1405}, "6": {"win_rate": 0.489, "games": 3805}, "35": {"win_rate": 0.493, "games": 7335}, "71": {"win_rate": 0.488, "games": 6072}, "80": {"win_rate": 0.449, "games": 813}, "38": {"win_rate": 0.513, "games": 2155}, "90": {"win_rate": 0.469, "games": 1294}, "136": {"win_rate": 0.5, "games": 1095}, "67": {"win_rate": 0.446, "games": 3409}, "21": {"win_rate": 0.514, "games": 3405}, "131": {"win_rate": 0.504, "games": 1007}, "81": {"win_rate": 0.486, "games": 1216}, "104": {"win_rate": 0.459, "games": 5431}, "126": {"win_rate": 0.48, "games": 2026}, "91": {"win_rate": 0.461, "games": 772}, "55": {"win_rate": 0.49, "games": 473}, "40": {"win_rate": 0.498, "games": 5155}, "94": {"win_rate": 0.468, "games": 1567}, "72": {"win_rate": 0.546, "games": 1158}, "9": {"win_rate": 0.477, "games": 2298}, "29": {"win_rate": 0.45, "games": 5124}, "12": {"win_rate": 0.423, "games": 2564}, "102": {"win_rate": 0.451, "games": 1099}, "61": {"win_rate": 0.447, "games": 792}, "113": {"win_rate": 0.438, "games": 837}, "77": {"win_rate": 0.48, "games": 250}, "78": {"win_rate": 0.438, "games": 395}, "89": {"win_rate": 0.432, "games": 548}}, "with": {"136": {"win_rate": 0.537, "games": 863}, "17": {"win_rate": 0.503, "games": 1980}, "55": {"win_rate": 0.525, "games": 383}, "120": {"win_rate": 0.523, "games": 1895}, "5": {"win_rate": 0.542, "games": 2448}, "62": {"win_rate": 0.528, "games": 758}, "92": {"win_rate": 0.573, "games": 267}, "44": {"win_rate": 0.529, "games": 4296}, "104": {"win_rate": 0.554, "games": 5066}, "51": {"win_rate": 0.498, "games": 657}, "112": {"win_rate": 0.522, "games": 689}, "4": {"win_rate": 0.546, "games": 1191}, "12": {"win_rate": 0.565, "games": 2307}, "113": {"win_rate": 0.536, "games": 705}, "78": {"win_rate": 0.525, "games": 387}, "105": {"win_rate": 0.548, "games": 1876}, "155": {"win_rate": 0.504, "games": 361}, "20": {"win_rate": 0.548, "games": 1718}, "2": {"win_rate": 0.545, "games": 5598}, "11": {"win_rate": 0.5, "games": 3479}, "74": {"win_rate": 0.545, "games": 4455}, "107": {"win_rate": 0.521, "games": 666}, "137": {"win_rate": 0.529, "games": 1177}, "14": {"win_rate": 0.52, "games": 7276}, "110": {"win_rate": 0.544, "games": 1432}, "66": {"win_rate": 0.493, "games": 71}, "15": {"win_rate": 0.512, "games": 1994}, "41": {"win_rate": 0.513, "games": 3670}, "33": {"win_rate": 0.513, "games": 636}, "31": {"win_rate": 0.531, "games": 2366}, "58": {"win_rate": 0.499, "games": 393}, "97": {"win_rate": 0.497, "games": 2749}, "36": {"win_rate": 0.531, "games": 4311}, "35": {"win_rate": 0.511, "games": 5584}, "54": {"win_rate": 0.536, "games": 4236}, "83": {"win_rate": 0.503, "games": 459}, "26": {"win_rate": 0.505, "games": 6111}, "21": {"win_rate": 0.485, "games": 2553}, "32": {"win_rate": 0.533, "games": 1491}, "34": {"win_rate": 0.455, "games": 639}, "8": {"win_rate": 0.525, "games": 4844}, "93": {"win_rate": 0.507, "games": 5276}, "50": {"win_rate": 0.522, "games": 720}, "69": {"win_rate": 0.467, "games": 2452}, "135": {"win_rate": 0.539, "games": 2089}, "145": {"win_rate": 0.493, "games": 1013}, "7": {"win_rate": 0.504, "games": 3298}, "73": {"win_rate": 0.516, "games": 3864}, "59": {"win_rate": 0.499, "games": 1252}, "42": {"win_rate": 0.547, "games": 4813}, "81": {"win_rate": 0.507, "games": 1168}, "60": {"win_rate": 0.521, "games": 2214}, "52": {"win_rate": 0.489, "games": 800}, "98": {"win_rate": 0.447, "games": 870}, "30": {"win_rate": 0.515, "games": 3718}, "88": {"win_rate": 0.518, "games": 1528}, "48": {"win_rate": 0.517, "games": 2280}, "27": {"win_rate": 0.527, "games": 3288}, "38": {"win_rate": 0.482, "games": 1924}, "39": {"win_rate": 0.487, "games": 4238}, "29": {"win_rate": 0.528, "games": 4851}, "16": {"win_rate": 0.498, "games": 1888}, "96": {"win_rate": 0.486, "games": 1618}, "138": {"win_rate": 0.494, "games": 1636}, "100": {"win_rate": 0.484, "games": 1247}, "109": {"win_rate": 0.496, "games": 629}, "3": {"win_rate": 0.507, "games": 371}, "114": {"win_rate": 0.463, "games": 2613}, "1": {"win_rate": 0.481, "games": 3304}, "85": {"win_rate": 0.523, "games": 2157}, "37": {"win_rate": 0.506, "games": 1599}, "6": {"win_rate": 0.505, "games": 3484}, "19": {"win_rate": 0.46, "games": 1886}, "84": {"win_rate": 0.513, "games": 4366}, "63": {"win_rate": 0.466, "games": 2586}, "129": {"win_rate": 0.444, "games": 2273}, "95": {"win_rate": 0.504, "games": 532}, "71": {"win_rate": 0.503, "games": 4747}, "80": {"win_rate": 0.541, "games": 695}, "79": {"win_rate": 0.46, "games": 433}, "56": {"win_rate": 0.514, "games": 1313}, "123": {"win_rate": 0.487, "games": 1625}, "64": {"win_rate": 0.465, "games": 2106}, "76": {"win_rate": 0.486, "games": 1384}, "22": {"win_rate": 0.505, "games": 3350}, "68": {"win_rate": 0.492, "games": 1259}, "47": {"win_rate": 0.489, "games": 2106}, "89": {"win_rate": 0.501, "games": 439}, "86": {"win_rate": 0.498, "games": 4620}, "28": {"win_rate": 0.508, "games": 2773}, "70": {"win_rate": 0.468, "games": 2014}, "128": {"win_rate": 0.472, "games": 1086}, "126": {"win_rate": 0.5, "games": 1623}, "82": {"win_rate": 0.504, "games": 687}, "67": {"win_rate": 0.536, "games": 3526}, "99": {"win_rate": 0.492, "games": 2508}, "91": {"win_rate": 0.514, "games": 488}, "102": {"win_rate": 0.506, "games": 722}, "77": {"win_rate": 0.462, "games": 197}, "111": {"win_rate": 0.484, "games": 556}, "108": {"win_rate": 0.506, "games": 1849}, "101": {"win_rate": 0.482, "games": 2423}, "121": {"win_rate": 0.506, "games": 749}, "119": {"win_rate": 0.468, "games": 867}, "106": {"win_rate": 0.477, "games": 1985}, "13": {"win_rate": 0.465, "games": 1149}, "65": {"win_rate": 0.483, "games": 710}, "10": {"win_rate": 0.468, "games": 1030}, "46": {"win_rate": 0.451, "games": 1344}, "23": {"win_rate": 0.486, "games": 1363}, "87": {"win_rate": 0.48, "games": 1476}, "25": {"win_rate": 0.469, "games": 3383}, "40": {"win_rate": 0.47, "games": 2842}, "49": {"win_rate": 0.476, "games": 1558}, "18": {"win_rate": 0.482, "games": 1316}, "72": {"win_rate": 0.419, "games": 927}, "90": {"win_rate": 0.504, "games": 912}, "57": {"win_rate": 0.472, "games": 576}, "9": {"win_rate": 0.478, "games": 1425}, "61": {"win_rate": 0.486, "games": 576}, "53": {"win_rate": 0.41, "games": 1620}, "94": {"win_rate": 0.487, "games": 1426}, "43": {"win_rate": 0.453, "games": 1145}, "45": {"win_rate": 0.477, "games": 687}, "131": {"win_rate": 0.452, "games": 569}, "103": {"win_rate": 0.463, "games": 190}}}, "HERALD_GUARDIAN": {"vs": {"52": {"win_rate": 0.582, "games": 727}, "91": {"win_rate": 0.556, "games": 644}, "103": {"win_rate": 0.553, "games": 208}, "77": {"win_rate": 0.616, "games": 190}, "135": {"win_rate": 0.536, "games": 1264}, "155": {"win_rate": 0.592, "games": 360}, "137": {"win_rate": 0.548, "games": 842}, "96": {"win_rate": 0.561, "games": 1331}, "63": {"win_rate": 0.579, "games": 2724}, "7": {"win_rate": 0.554, "games": 3518}, "99": {"win_rate": 0.516, "games": 3254}, "106": {"win_rate": 0.561, "games": 1302}, "121": {"win_rate": 0.524, "games": 1039}, "13": {"win_rate": 0.587, "games": 829}, "54": {"win_rate": 0.52, "games": 2963}, "100": {"win_rate": 0.576, "games": 1023}, "131": {"win_rate": 0.557, "games": 598}, "18": {"win_rate": 0.541, "games": 1331}, "62": {"win_rate": 0.537, "games": 1258}, "16": {"win_rate": 0.524, "games": 1764}, "64": {"win_rate": 0.552, "games": 2812}, "36": {"win_rate": 0.505, "games": 4043}, "110": {"win_rate": 0.514, "games": 1188}, "33": {"win_rate": 0.532, "games": 832}, "114": {"win_rate": 0.573, "games": 2104}, "108": {"win_rate": 0.512, "games": 1427}, "31": {"win_rate": 0.51, "games": 3072}, "68": {"win_rate": 0.527, "games": 1891}, "39": {"win_rate": 0.555, "games": 3473}, "46": {"win_rate": 0.569, "games": 1289}, "129": {"win_rate": 0.582, "games": 1394}, "30": {"win_rate": 0.511, "games": 5517}, "101": {"win_rate": 0.535, "games": 3875}, "14": {"win_rate": 0.522, "games": 7397}, "107": {"win_rate": 0.548, "games": 504}, "41": {"win_rate": 0.53, "games": 2916}, "88": {"win_rate": 0.508, "games": 1499}, "123": {"win_rate": 0.536, "games": 2127}, "2": {"win_rate": 0.493, "games": 4674}, "86": {"win_rate": 0.536, "games": 4501}, "27": {"win_rate": 0.504, "games": 4899}, "6": {"win_rate": 0.533, "games": 3783}, "22": {"win_rate": 0.51, "games": 4740}, "32": {"win_rate": 0.502, "games": 1951}, "28": {"win_rate": 0.523, "games": 2510}, "47": {"win_rate": 0.542, "games": 2853}, "128": {"win_rate": 0.547, "games": 1143}, "49": {"win_rate": 0.526, "games": 1736}, "120": {"win_rate": 0.547, "games": 1096}, "20": {"win_rate": 0.494, "games": 1910}, "44": {"win_rate": 0.508, "games": 4340}, "69": {"win_rate": 0.567, "games": 1689}, "65": {"win_rate": 0.536, "games": 509}, "4": {"win_rate": 0.498, "games": 1400}, "5": {"win_rate": 0.495, "games": 3894}, "57": {"win_rate": 0.534, "games": 698}, "23": {"win_rate": 0.535, "games": 1212}, "109": {"win_rate": 0.54, "games": 667}, "17": {"win_rate": 0.555, "games": 1476}, "105": {"win_rate": 0.496, "games": 2784}, "73": {"win_rate": 0.502, "games": 2645}, "34": {"win_rate": 0.587, "games": 668}, "87": {"win_rate": 0.536, "games": 1757}, "26": {"win_rate": 0.525, "games": 7818}, "59": {"win_rate": 0.548, "games": 1632}, "92": {"win_rate": 0.499, "games": 337}, "85": {"win_rate": 0.501, "games": 2727}, "70": {"win_rate": 0.557, "games": 1537}, "25": {"win_rate": 0.545, "games": 3818}, "81": {"win_rate": 0.514, "games": 1377}, "1": {"win_rate": 0.534, "games": 3276}, "29": {"win_rate": 0.488, "games": 3815}, "60": {"win_rate": 0.517, "games": 1371}, "112": {"win_rate": 0.524, "games": 881}, "35": {"win_rate": 0.509, "games": 6656}, "111": {"win_rate": 0.529, "games": 620}, "37": {"win_rate": 0.505, "games": 2381}, "95": {"win_rate": 0.499, "games": 827}, "83": {"win_rate": 0.518, "games": 629}, "50": {"win_rate": 0.514, "games": 1044}, "98": {"win_rate": 0.576, "games": 627}, "9": {"win_rate": 0.504, "games": 2059}, "138": {"win_rate": 0.52, "games": 1401}, "43": {"win_rate": 0.537, "games": 1434}, "48": {"win_rate": 0.498, "games": 2078}, "21": {"win_rate": 0.546, "games": 3264}, "56": {"win_rate": 0.505, "games": 1774}, "76": {"win_rate": 0.536, "games": 1221}, "11": {"win_rate": 0.527, "games": 2967}, "97": {"win_rate": 0.533, "games": 1849}, "67": {"win_rate": 0.451, "games": 3199}, "74": {"win_rate": 0.49, "games": 4298}, "61": {"win_rate": 0.498, "games": 929}, "71": {"win_rate": 0.498, "games": 4879}, "80": {"win_rate": 0.485, "games": 631}, "84": {"win_rate": 0.486, "games": 6024}, "10": {"win_rate": 0.53, "games": 872}, "40": {"win_rate": 0.525, "games": 4100}, "72": {"win_rate": 0.582, "games": 893}, "53": {"win_rate": 0.562, "games": 2327}, "38": {"win_rate": 0.525, "games": 1607}, "15": {"win_rate": 0.507, "games": 2144}, "119": {"win_rate": 0.538, "games": 1270}, "126": {"win_rate": 0.503, "games": 1143}, "94": {"win_rate": 0.484, "games": 1446}, "93": {"win_rate": 0.5, "games": 4085}, "51": {"win_rate": 0.531, "games": 671}, "45": {"win_rate": 0.508, "games": 1062}, "79": {"win_rate": 0.558, "games": 496}, "19": {"win_rate": 0.553, "games": 1463}, "89": {"win_rate": 0.491, "games": 660}, "8": {"win_rate": 0.486, "games": 4526}, "42": {"win_rate": 0.442, "games": 4034}, "113": {"win_rate": 0.488, "games": 797}, "55": {"win_rate": 0.507, "games": 410}, "3": {"win_rate": 0.497, "games": 517}, "104": {"win_rate": 0.463, "games": 4470}, "90": {"win_rate": 0.499, "games": 974}, "136": {"win_rate": 0.505, "games": 933}, "145": {"win_rate": 0.514, "games": 769}, "66": {"win_rate": 0.527, "games": 93}, "58": {"win_rate": 0.496, "games": 838}, "102": {"win_rate": 0.469, "games": 802}, "78": {"win_rate": 0.47, "games": 298}, "12": {"win_rate": 0.436, "games": 2367}, "82": {"win_rate": 0.457, "games": 604}}, "with": {"66": {"win_rate": 0.54, "games": 63}, "113": {"win_rate": 0.565, "games": 632}, "112": {"win_rate": 0.545, "games": 556}, "77": {"win_rate": 0.497, "games": 185}, "107": {"win_rate": 0.522, "games": 381}, "33": {"win_rate": 0.538, "games": 483}, "69": {"win_rate": 0.491, "games": 1624}, "34": {"win_rate": 0.468, "games": 513}, "121": {"win_rate": 0.552, "games": 560}, "55": {"win_rate": 0.521, "games": 303}, "96": {"win_rate": 0.529, "games": 1379}, "15": {"win_rate": 0.53, "games": 1795}, "3": {"win_rate": 0.529, "games": 293}, "82": {"win_rate": 0.542, "games": 554}, "137": {"win_rate": 0.543, "games": 816}, "41": {"win_rate": 0.529, "games": 2997}, "91": {"win_rate": 0.548, "games": 392}, "14": {"win_rate": 0.536, "games": 6058}, "120": {"win_rate": 0.505, "games": 928}, "54": {"win_rate": 0.547, "games": 2997}, "32": {"win_rate": 0.55, "games": 1739}, "26": {"win_rate": 0.521, "games": 4892}, "95": {"win_rate": 0.542, "games": 771}, "136": {"win_rate": 0.51, "games": 763}, "39": {"win_rate": 0.502, "games": 2746}, "100": {"win_rate": 0.489, "games": 790}, "19": {"win_rate": 0.476, "games": 1353}, "94": {"win_rate": 0.545, "games": 1301}, "104": {"win_rate": 0.555, "games": 4264}, "10": {"win_rate": 0.503, "games": 790}, "65": {"win_rate": 0.511, "games": 417}, "2": {"win_rate": 0.557, "games": 4619}, "74": {"win_rate": 0.542, "games": 3202}, "36": {"win_rate": 0.552, "games": 3526}, "18": {"win_rate": 0.518, "games": 1321}, "93": {"win_rate": 0.526, "games": 4023}, "31": {"win_rate": 0.544, "games": 1732}, "28": {"win_rate": 0.524, "games": 2381}, "52": {"win_rate": 0.518, "games": 616}, "44": {"win_rate": 0.536, "games": 4275}, "23": {"win_rate": 0.507, "games": 1080}, "119": {"win_rate": 0.488, "games": 752}, "76": {"win_rate": 0.496, "games": 1098}, "5": {"win_rate": 0.545, "games": 2366}, "145": {"win_rate": 0.494, "games": 674}, "20": {"win_rate": 0.548, "games": 1275}, "29": {"win_rate": 0.547, "games": 3510}, "68": {"win_rate": 0.523, "games": 1158}, "13": {"win_rate": 0.474, "games": 713}, "12": {"win_rate": 0.551, "games": 2203}, "43": {"win_rate": 0.495, "games": 1108}, "135": {"win_rate": 0.547, "games": 1220}, "38": {"win_rate": 0.499, "games": 1508}, "71": {"win_rate": 0.529, "games": 3843}, "81": {"win_rate": 0.522, "games": 1405}, "6": {"win_rate": 0.511, "games": 3229}, "84": {"win_rate": 0.539, "games": 4558}, "67": {"win_rate": 0.574, "games": 3139}, "123": {"win_rate": 0.508, "games": 1318}, "70": {"win_rate": 0.477, "games": 1465}, "35": {"win_rate": 0.522, "games": 5545}, "45": {"win_rate": 0.51, "games": 683}, "129": {"win_rate": 0.464, "games": 1333}, "63": {"win_rate": 0.483, "games": 2451}, "97": {"win_rate": 0.491, "games": 1422}, "1": {"win_rate": 0.498, "games": 2974}, "72": {"win_rate": 0.44, "games": 723}, "98": {"win_rate": 0.453, "games": 603}, "8": {"win_rate": 0.528, "games": 4404}, "49": {"win_rate": 0.511, "games": 1627}, "47": {"win_rate": 0.495, "games": 2243}, "11": {"win_rate": 0.496, "games": 2520}, "53": {"win_rate": 0.458, "games": 1665}, "30": {"win_rate": 0.53, "games": 3203}, "58": {"win_rate": 0.499, "games": 539}, "46": {"win_rate": 0.474, "games": 1119}, "126": {"win_rate": 0.513, "games": 947}, "16": {"win_rate": 0.522, "games": 1566}, "108": {"win_rate": 0.531, "games": 1320}, "42": {"win_rate": 0.567, "games": 3894}, "64": {"win_rate": 0.493, "games": 1681}, "7": {"win_rate": 0.502, "games": 2799}, "40": {"win_rate": 0.493, "games": 2410}, "4": {"win_rate": 0.533, "games": 1320}, "83": {"win_rate": 0.506, "games": 498}, "51": {"win_rate": 0.482, "games": 514}, "9": {"win_rate": 0.519, "games": 1402}, "48": {"win_rate": 0.523, "games": 1872}, "106": {"win_rate": 0.492, "games": 1160}, "56": {"win_rate": 0.515, "games": 1538}, "138": {"win_rate": 0.502, "games": 1313}, "105": {"win_rate": 0.531, "games": 1818}, "114": {"win_rate": 0.467, "games": 1891}, "17": {"win_rate": 0.473, "games": 1339}, "57": {"win_rate": 0.494, "games": 547}, "60": {"win_rate": 0.505, "games": 1362}, "89": {"win_rate": 0.516, "games": 589}, "90": {"win_rate": 0.497, "games": 719}, "59": {"win_rate": 0.476, "games": 1384}, "109": {"win_rate": 0.485, "games": 590}, "25": {"win_rate": 0.477, "games": 2755}, "87": {"win_rate": 0.487, "games": 969}, "27": {"win_rate": 0.524, "games": 2926}, "73": {"win_rate": 0.519, "games": 2442}, "79": {"win_rate": 0.446, "games": 316}, "103": {"win_rate": 0.515, "games": 165}, "50": {"win_rate": 0.499, "games": 639}, "37": {"win_rate": 0.509, "games": 1407}, "22": {"win_rate": 0.514, "games": 2956}, "86": {"win_rate": 0.489, "games": 2795}, "21": {"win_rate": 0.465, "games": 2363}, "62": {"win_rate": 0.495, "games": 932}, "85": {"win_rate": 0.513, "games": 2157}, "99": {"win_rate": 0.523, "games": 2926}, "92": {"win_rate": 0.514, "games": 257}, "128": {"win_rate": 0.471, "games": 717}, "101": {"win_rate": 0.487, "games": 2200}, "155": {"win_rate": 0.461, "games": 245}, "110": {"win_rate": 0.505, "games": 818}, "61": {"win_rate": 0.494, "games": 678}, "131": {"win_rate": 0.463, "games": 382}, "102": {"win_rate": 0.493, "games": 619}, "78": {"win_rate": 0.485, "games": 241}, "88": {"win_rate": 0.496, "games": 1090}, "80": {"win_rate": 0.497, "games": 537}, "111": {"win_rate": 0.454, "games": 381}}}}