{"DIVINE_IMMORTAL": {"vs": {"95": {"win_rate": 0.598, "games": 92}, "155": {"win_rate": 0.573, "games": 157}, "1": {"win_rate": 0.588, "games": 517}, "112": {"win_rate": 0.523, "games": 409}, "51": {"win_rate": 0.541, "games": 281}, "17": {"win_rate": 0.575, "games": 541}, "93": {"win_rate": 0.548, "games": 1058}, "136": {"win_rate": 0.553, "games": 394}, "90": {"win_rate": 0.51, "games": 498}, "99": {"win_rate": 0.552, "games": 545}, "7": {"win_rate": 0.527, "games": 916}, "19": {"win_rate": 0.554, "games": 891}, "76": {"win_rate": 0.54, "games": 365}, "36": {"win_rate": 0.527, "games": 824}, "46": {"win_rate": 0.579, "games": 437}, "16": {"win_rate": 0.559, "games": 560}, "61": {"win_rate": 0.522, "games": 113}, "12": {"win_rate": 0.482, "games": 602}, "27": {"win_rate": 0.494, "games": 1362}, "80": {"win_rate": 0.478, "games": 297}, "64": {"win_rate": 0.557, "games": 765}, "37": {"win_rate": 0.531, "games": 616}, "29": {"win_rate": 0.504, "games": 1356}, "70": {"win_rate": 0.532, "games": 523}, "28": {"win_rate": 0.503, "games": 783}, "137": {"win_rate": 0.501, "games": 441}, "145": {"win_rate": 0.522, "games": 475}, "92": {"win_rate": 0.433, "games": 157}, "21": {"win_rate": 0.514, "games": 703}, "72": {"win_rate": 0.573, "games": 307}, "6": {"win_rate": 0.501, "games": 726}, "97": {"win_rate": 0.521, "games": 940}, "135": {"win_rate": 0.476, "games": 781}, "8": {"win_rate": 0.497, "games": 1034}, "100": {"win_rate": 0.513, "games": 948}, "56": {"win_rate": 0.479, "games": 357}, "23": {"win_rate": 0.509, "games": 454}, "14": {"win_rate": 0.512, "games": 2244}, "138": {"win_rate": 0.519, "games": 578}, "47": {"win_rate": 0.505, "games": 467}, "54": {"win_rate": 0.481, "games": 1185}, "113": {"win_rate": 0.503, "games": 181}, "5": {"win_rate": 0.507, "games": 896}, "79": {"win_rate": 0.534, "games": 369}, "30": {"win_rate": 0.521, "games": 973}, "69": {"win_rate": 0.531, "games": 815}, "120": {"win_rate": 0.507, "games": 1295}, "50": {"win_rate": 0.489, "games": 270}, "128": {"win_rate": 0.52, "games": 523}, "102": {"win_rate": 0.492, "games": 197}, "66": {"win_rate": 0.514, "games": 37}, "31": {"win_rate": 0.497, "games": 1115}, "86": {"win_rate": 0.49, "games": 2281}, "96": {"win_rate": 0.54, "games": 335}, "82": {"win_rate": 0.491, "games": 226}, "74": {"win_rate": 0.468, "games": 1620}, "25": {"win_rate": 0.506, "games": 860}, "91": {"win_rate": 0.479, "games": 334}, "55": {"win_rate": 0.5, "games": 138}, "98": {"win_rate": 0.558, "games": 224}, "39": {"win_rate": 0.498, "games": 1393}, "77": {"win_rate": 0.494, "games": 79}, "85": {"win_rate": 0.47, "games": 656}, "84": {"win_rate": 0.497, "games": 879}, "43": {"win_rate": 0.5, "games": 392}, "71": {"win_rate": 0.498, "games": 1545}, "57": {"win_rate": 0.49, "games": 247}, "45": {"win_rate": 0.476, "games": 296}, "123": {"win_rate": 0.501, "games": 761}, "101": {"win_rate": 0.517, "games": 947}, "63": {"win_rate": 0.518, "games": 677}, "126": {"win_rate": 0.504, "games": 933}, "83": {"win_rate": 0.466, "games": 249}, "107": {"win_rate": 0.476, "games": 399}, "26": {"win_rate": 0.5, "games": 2184}, "22": {"win_rate": 0.487, "games": 1227}, "65": {"win_rate": 0.468, "games": 523}, "53": {"win_rate": 0.525, "games": 436}, "48": {"win_rate": 0.478, "games": 808}, "110": {"win_rate": 0.457, "games": 863}, "41": {"win_rate": 0.489, "games": 753}, "60": {"win_rate": 0.46, "games": 874}, "20": {"win_rate": 0.466, "games": 579}, "89": {"win_rate": 0.482, "games": 114}, "62": {"win_rate": 0.461, "games": 343}, "33": {"win_rate": 0.463, "games": 162}, "59": {"win_rate": 0.466, "games": 509}, "13": {"win_rate": 0.495, "games": 545}, "108": {"win_rate": 0.49, "games": 543}, "9": {"win_rate": 0.485, "games": 493}, "38": {"win_rate": 0.486, "games": 729}, "42": {"win_rate": 0.473, "games": 761}, "106": {"win_rate": 0.48, "games": 911}, "73": {"win_rate": 0.482, "games": 1473}, "32": {"win_rate": 0.463, "games": 335}, "15": {"win_rate": 0.499, "games": 469}, "131": {"win_rate": 0.486, "games": 529}, "11": {"win_rate": 0.5, "games": 964}, "111": {"win_rate": 0.469, "games": 356}, "109": {"win_rate": 0.448, "games": 299}, "40": {"win_rate": 0.498, "games": 1230}, "78": {"win_rate": 0.45, "games": 191}, "103": {"win_rate": 0.451, "games": 102}, "129": {"win_rate": 0.531, "games": 875}, "35": {"win_rate": 0.498, "games": 868}, "44": {"win_rate": 0.482, "games": 822}, "10": {"win_rate": 0.492, "games": 329}, "34": {"win_rate": 0.523, "games": 214}, "88": {"win_rate": 0.447, "games": 636}, "114": {"win_rate": 0.489, "games": 1080}, "2": {"win_rate": 0.452, "games": 1036}, "52": {"win_rate": 0.463, "games": 337}, "75": {"win_rate": 0.466, "games": 796}, "3": {"win_rate": 0.44, "games": 241}, "67": {"win_rate": 0.452, "games": 493}, "4": {"win_rate": 0.442, "games": 242}, "119": {"win_rate": 0.469, "games": 450}, "104": {"win_rate": 0.442, "games": 989}, "105": {"win_rate": 0.429, "games": 756}, "81": {"win_rate": 0.465, "games": 202}, "58": {"win_rate": 0.464, "games": 151}, "121": {"win_rate": 0.425, "games": 435}, "94": {"win_rate": 0.444, "games": 293}, "18": {"win_rate": 0.443, "games": 244}, "68": {"win_rate": 0.44, "games": 461}, "49": {"win_rate": 0.427, "games": 274}}, "with": {"77": {"win_rate": 0.57, "games": 79}, "83": {"win_rate": 0.59, "games": 105}, "92": {"win_rate": 0.641, "games": 117}, "85": {"win_rate": 0.588, "games": 425}, "33": {"win_rate": 0.58, "games": 131}, "84": {"win_rate": 0.556, "games": 500}, "46": {"win_rate": 0.489, "games": 421}, "37": {"win_rate": 0.528, "games": 199}, "59": {"win_rate": 0.56, "games": 432}, "61": {"win_rate": 0.541, "games": 135}, "95": {"win_rate": 0.524, "games": 103}, "56": {"win_rate": 0.567, "games": 383}, "90": {"win_rate": 0.555, "games": 393}, "50": {"win_rate": 0.543, "games": 105}, "114": {"win_rate": 0.508, "games": 1100}, "49": {"win_rate": 0.504, "games": 240}, "43": {"win_rate": 0.519, "games": 376}, "25": {"win_rate": 0.516, "games": 764}, "58": {"win_rate": 0.512, "games": 86}, "11": {"win_rate": 0.502, "games": 925}, "62": {"win_rate": 0.547, "games": 287}, "23": {"win_rate": 0.519, "games": 312}, "36": {"win_rate": 0.518, "games": 960}, "110": {"win_rate": 0.551, "games": 644}, "32": {"win_rate": 0.537, "games": 259}, "101": {"win_rate": 0.494, "games": 557}, "111": {"win_rate": 0.526, "games": 97}, "112": {"win_rate": 0.55, "games": 200}, "47": {"win_rate": 0.517, "games": 441}, "40": {"win_rate": 0.496, "games": 585}, "78": {"win_rate": 0.542, "games": 177}, "73": {"win_rate": 0.514, "games": 1355}, "29": {"win_rate": 0.524, "games": 1429}, "54": {"win_rate": 0.538, "games": 1191}, "35": {"win_rate": 0.49, "games": 788}, "66": {"win_rate": 0.5, "games": 16}, "28": {"win_rate": 0.522, "games": 766}, "67": {"win_rate": 0.52, "games": 471}, "44": {"win_rate": 0.499, "games": 813}, "52": {"win_rate": 0.509, "games": 346}, "53": {"win_rate": 0.472, "games": 326}, "69": {"win_rate": 0.481, "games": 783}, "81": {"win_rate": 0.495, "games": 192}, "9": {"win_rate": 0.503, "games": 330}, "106": {"win_rate": 0.507, "games": 913}, "38": {"win_rate": 0.501, "games": 720}, "94": {"win_rate": 0.507, "games": 229}, "102": {"win_rate": 0.515, "games": 136}, "42": {"win_rate": 0.513, "games": 753}, "64": {"win_rate": 0.464, "games": 321}, "17": {"win_rate": 0.477, "games": 704}, "104": {"win_rate": 0.519, "games": 874}, "57": {"win_rate": 0.507, "games": 142}, "19": {"win_rate": 0.475, "games": 758}, "22": {"win_rate": 0.504, "games": 840}, "65": {"win_rate": 0.521, "games": 426}, "15": {"win_rate": 0.481, "games": 441}, "89": {"win_rate": 0.504, "games": 121}, "98": {"win_rate": 0.44, "games": 284}, "74": {"win_rate": 0.529, "games": 1439}, "99": {"win_rate": 0.478, "games": 577}, "70": {"win_rate": 0.481, "games": 630}, "41": {"win_rate": 0.497, "games": 791}, "135": {"win_rate": 0.529, "games": 854}, "20": {"win_rate": 0.517, "games": 317}, "39": {"win_rate": 0.495, "games": 1456}, "68": {"win_rate": 0.475, "games": 177}, "103": {"win_rate": 0.52, "games": 50}, "18": {"win_rate": 0.493, "games": 217}, "48": {"win_rate": 0.505, "games": 679}, "55": {"win_rate": 0.493, "games": 136}, "120": {"win_rate": 0.49, "games": 1173}, "60": {"win_rate": 0.521, "games": 787}, "71": {"win_rate": 0.491, "games": 1203}, "105": {"win_rate": 0.517, "games": 476}, "128": {"win_rate": 0.475, "games": 318}, "97": {"win_rate": 0.48, "games": 848}, "4": {"win_rate": 0.508, "games": 236}, "6": {"win_rate": 0.498, "games": 649}, "119": {"win_rate": 0.48, "games": 273}, "126": {"win_rate": 0.478, "games": 957}, "14": {"win_rate": 0.484, "games": 1558}, "30": {"win_rate": 0.473, "games": 357}, "1": {"win_rate": 0.464, "games": 567}, "63": {"win_rate": 0.463, "games": 672}, "72": {"win_rate": 0.426, "games": 235}, "3": {"win_rate": 0.509, "games": 108}, "13": {"win_rate": 0.477, "games": 505}, "12": {"win_rate": 0.524, "games": 618}, "5": {"win_rate": 0.486, "games": 296}, "123": {"win_rate": 0.479, "games": 472}, "107": {"win_rate": 0.5, "games": 346}, "145": {"win_rate": 0.476, "games": 399}, "76": {"win_rate": 0.472, "games": 320}, "7": {"win_rate": 0.486, "games": 790}, "21": {"win_rate": 0.481, "games": 518}, "108": {"win_rate": 0.478, "games": 479}, "8": {"win_rate": 0.496, "games": 859}, "86": {"win_rate": 0.495, "games": 1419}, "129": {"win_rate": 0.429, "games": 889}, "100": {"win_rate": 0.478, "games": 567}, "80": {"win_rate": 0.521, "games": 282}, "109": {"win_rate": 0.508, "games": 301}, "138": {"win_rate": 0.465, "games": 555}, "26": {"win_rate": 0.467, "games": 1088}, "2": {"win_rate": 0.488, "games": 1056}, "75": {"win_rate": 0.47, "games": 355}, "93": {"win_rate": 0.471, "games": 1384}, "88": {"win_rate": 0.493, "games": 406}, "121": {"win_rate": 0.497, "games": 185}, "45": {"win_rate": 0.489, "games": 139}, "136": {"win_rate": 0.462, "games": 260}, "131": {"win_rate": 0.464, "games": 222}, "16": {"win_rate": 0.434, "games": 541}, "10": {"win_rate": 0.447, "games": 398}, "34": {"win_rate": 0.414, "games": 222}, "137": {"win_rate": 0.477, "games": 432}, "27": {"win_rate": 0.483, "games": 528}, "79": {"win_rate": 0.431, "games": 153}, "113": {"win_rate": 0.462, "games": 195}, "96": {"win_rate": 0.418, "games": 361}, "51": {"win_rate": 0.462, "games": 158}, "82": {"win_rate": 0.463, "games": 218}, "155": {"win_rate": 0.45, "games": 131}, "91": {"win_rate": 0.466, "games": 131}, "31": {"win_rate": 0.449, "games": 372}}}, "LEGEND_ANCIENT": {"vs": {"78": {"win_rate": 0.536, "games": 220}, "66": {"win_rate": 0.563, "games": 71}, "98": {"win_rate": 0.6, "games": 427}, "89": {"win_rate": 0.524, "games": 187}, "90": {"win_rate": 0.498, "games": 679}, "51": {"win_rate": 0.539, "games": 386}, "82": {"win_rate": 0.506, "games": 338}, "18": {"win_rate": 0.517, "games": 553}, "12": {"win_rate": 0.478, "games": 946}, "31": {"win_rate": 0.502, "games": 1959}, "9": {"win_rate": 0.518, "games": 985}, "93": {"win_rate": 0.515, "games": 2118}, "8": {"win_rate": 0.497, "games": 2220}, "2": {"win_rate": 0.492, "games": 2256}, "91": {"win_rate": 0.502, "games": 422}, "70": {"win_rate": 0.535, "games": 1029}, "7": {"win_rate": 0.505, "games": 1702}, "145": {"win_rate": 0.528, "games": 572}, "41": {"win_rate": 0.505, "games": 1474}, "5": {"win_rate": 0.503, "games": 1773}, "85": {"win_rate": 0.483, "games": 1151}, "1": {"win_rate": 0.527, "games": 1177}, "28": {"win_rate": 0.497, "games": 1327}, "26": {"win_rate": 0.513, "games": 4308}, "47": {"win_rate": 0.509, "games": 892}, "15": {"win_rate": 0.512, "games": 926}, "55": {"win_rate": 0.5, "games": 184}, "17": {"win_rate": 0.537, "games": 955}, "60": {"win_rate": 0.479, "games": 1317}, "75": {"win_rate": 0.507, "games": 1744}, "101": {"win_rate": 0.517, "games": 1816}, "88": {"win_rate": 0.491, "games": 1024}, "131": {"win_rate": 0.517, "games": 586}, "119": {"win_rate": 0.517, "games": 627}, "128": {"win_rate": 0.529, "games": 864}, "61": {"win_rate": 0.492, "games": 238}, "44": {"win_rate": 0.51, "games": 1735}, "129": {"win_rate": 0.556, "games": 1321}, "29": {"win_rate": 0.478, "games": 2416}, "14": {"win_rate": 0.504, "games": 3920}, "74": {"win_rate": 0.466, "games": 3014}, "97": {"win_rate": 0.508, "games": 1780}, "39": {"win_rate": 0.507, "games": 2290}, "32": {"win_rate": 0.476, "games": 580}, "59": {"win_rate": 0.501, "games": 710}, "16": {"win_rate": 0.514, "games": 990}, "112": {"win_rate": 0.482, "games": 504}, "103": {"win_rate": 0.47, "games": 132}, "71": {"win_rate": 0.498, "games": 2939}, "135": {"win_rate": 0.465, "games": 1252}, "94": {"win_rate": 0.488, "games": 608}, "50": {"win_rate": 0.482, "games": 533}, "13": {"win_rate": 0.525, "games": 747}, "100": {"win_rate": 0.511, "games": 1220}, "107": {"win_rate": 0.481, "games": 524}, "30": {"win_rate": 0.493, "games": 2403}, "43": {"win_rate": 0.507, "games": 631}, "42": {"win_rate": 0.463, "games": 1774}, "79": {"win_rate": 0.542, "games": 513}, "86": {"win_rate": 0.485, "games": 3845}, "73": {"win_rate": 0.487, "games": 2253}, "106": {"win_rate": 0.5, "games": 1341}, "123": {"win_rate": 0.499, "games": 1315}, "36": {"win_rate": 0.48, "games": 1831}, "126": {"win_rate": 0.492, "games": 1285}, "62": {"win_rate": 0.469, "games": 597}, "20": {"win_rate": 0.462, "games": 1141}, "22": {"win_rate": 0.49, "games": 2173}, "138": {"win_rate": 0.503, "games": 869}, "72": {"win_rate": 0.551, "games": 515}, "80": {"win_rate": 0.453, "games": 391}, "109": {"win_rate": 0.495, "games": 370}, "136": {"win_rate": 0.5, "games": 492}, "155": {"win_rate": 0.512, "games": 242}, "53": {"win_rate": 0.544, "games": 822}, "121": {"win_rate": 0.469, "games": 701}, "111": {"win_rate": 0.48, "games": 492}, "37": {"win_rate": 0.492, "games": 1195}, "54": {"win_rate": 0.456, "games": 2189}, "34": {"win_rate": 0.541, "games": 320}, "19": {"win_rate": 0.533, "games": 1244}, "69": {"win_rate": 0.524, "games": 1278}, "56": {"win_rate": 0.457, "games": 564}, "81": {"win_rate": 0.495, "games": 388}, "137": {"win_rate": 0.477, "games": 614}, "67": {"win_rate": 0.456, "games": 1308}, "84": {"win_rate": 0.482, "games": 2180}, "120": {"win_rate": 0.489, "games": 1464}, "76": {"win_rate": 0.499, "games": 688}, "110": {"win_rate": 0.453, "games": 1216}, "4": {"win_rate": 0.462, "games": 509}, "27": {"win_rate": 0.464, "games": 2537}, "99": {"win_rate": 0.492, "games": 1098}, "83": {"win_rate": 0.476, "games": 328}, "114": {"win_rate": 0.509, "games": 1480}, "113": {"win_rate": 0.465, "games": 346}, "48": {"win_rate": 0.472, "games": 1211}, "38": {"win_rate": 0.507, "games": 1091}, "64": {"win_rate": 0.515, "games": 1612}, "46": {"win_rate": 0.514, "games": 775}, "6": {"win_rate": 0.474, "games": 1494}, "108": {"win_rate": 0.477, "games": 924}, "10": {"win_rate": 0.503, "games": 495}, "35": {"win_rate": 0.486, "games": 2447}, "23": {"win_rate": 0.481, "games": 736}, "102": {"win_rate": 0.47, "games": 432}, "21": {"win_rate": 0.493, "games": 1401}, "58": {"win_rate": 0.496, "games": 232}, "52": {"win_rate": 0.487, "games": 468}, "68": {"win_rate": 0.49, "games": 977}, "40": {"win_rate": 0.49, "games": 2186}, "25": {"win_rate": 0.483, "games": 1753}, "63": {"win_rate": 0.504, "games": 1175}, "104": {"win_rate": 0.444, "games": 2063}, "105": {"win_rate": 0.45, "games": 1337}, "33": {"win_rate": 0.458, "games": 260}, "96": {"win_rate": 0.495, "games": 685}, "45": {"win_rate": 0.453, "games": 523}, "11": {"win_rate": 0.479, "games": 1837}, "57": {"win_rate": 0.474, "games": 369}, "3": {"win_rate": 0.44, "games": 343}, "49": {"win_rate": 0.47, "games": 577}, "92": {"win_rate": 0.398, "games": 186}, "77": {"win_rate": 0.427, "games": 96}, "65": {"win_rate": 0.429, "games": 552}, "95": {"win_rate": 0.427, "games": 218}}, "with": {"109": {"win_rate": 0.564, "games": 330}, "89": {"win_rate": 0.567, "games": 178}, "78": {"win_rate": 0.575, "games": 212}, "55": {"win_rate": 0.556, "games": 207}, "10": {"win_rate": 0.515, "games": 550}, "62": {"win_rate": 0.556, "games": 414}, "77": {"win_rate": 0.545, "games": 110}, "81": {"win_rate": 0.524, "games": 397}, "100": {"win_rate": 0.515, "games": 785}, "37": {"win_rate": 0.525, "games": 486}, "35": {"win_rate": 0.515, "games": 2072}, "3": {"win_rate": 0.541, "games": 157}, "96": {"win_rate": 0.49, "games": 663}, "47": {"win_rate": 0.514, "games": 864}, "21": {"win_rate": 0.501, "games": 1136}, "54": {"win_rate": 0.545, "games": 2078}, "36": {"win_rate": 0.527, "games": 1891}, "90": {"win_rate": 0.537, "games": 538}, "15": {"win_rate": 0.507, "games": 870}, "135": {"win_rate": 0.545, "games": 1243}, "82": {"win_rate": 0.525, "games": 341}, "46": {"win_rate": 0.478, "games": 712}, "155": {"win_rate": 0.489, "games": 180}, "25": {"win_rate": 0.499, "games": 1554}, "99": {"win_rate": 0.502, "games": 1011}, "106": {"win_rate": 0.502, "games": 1293}, "28": {"win_rate": 0.517, "games": 1349}, "83": {"win_rate": 0.512, "games": 164}, "38": {"win_rate": 0.479, "games": 1051}, "58": {"win_rate": 0.484, "games": 124}, "80": {"win_rate": 0.542, "games": 354}, "114": {"win_rate": 0.477, "games": 1535}, "33": {"win_rate": 0.512, "games": 205}, "98": {"win_rate": 0.437, "games": 494}, "110": {"win_rate": 0.533, "games": 887}, "120": {"win_rate": 0.499, "games": 1440}, "59": {"win_rate": 0.5, "games": 630}, "66": {"win_rate": 0.476, "games": 21}, "71": {"win_rate": 0.501, "games": 2091}, "48": {"win_rate": 0.511, "games": 1161}, "93": {"win_rate": 0.5, "games": 2522}, "20": {"win_rate": 0.53, "games": 674}, "69": {"win_rate": 0.464, "games": 1239}, "107": {"win_rate": 0.515, "games": 396}, "42": {"win_rate": 0.532, "games": 1723}, "79": {"win_rate": 0.453, "games": 203}, "67": {"win_rate": 0.529, "games": 1232}, "113": {"win_rate": 0.516, "games": 320}, "84": {"win_rate": 0.503, "games": 1405}, "14": {"win_rate": 0.496, "games": 2573}, "27": {"win_rate": 0.518, "games": 980}, "11": {"win_rate": 0.481, "games": 1693}, "63": {"win_rate": 0.465, "games": 1156}, "43": {"win_rate": 0.484, "games": 618}, "64": {"win_rate": 0.461, "games": 725}, "94": {"win_rate": 0.504, "games": 546}, "138": {"win_rate": 0.484, "games": 821}, "56": {"win_rate": 0.524, "games": 565}, "126": {"win_rate": 0.495, "games": 1173}, "76": {"win_rate": 0.48, "games": 691}, "121": {"win_rate": 0.513, "games": 343}, "40": {"win_rate": 0.474, "games": 1180}, "2": {"win_rate": 0.511, "games": 2292}, "53": {"win_rate": 0.437, "games": 641}, "65": {"win_rate": 0.498, "games": 452}, "86": {"win_rate": 0.499, "games": 2468}, "41": {"win_rate": 0.493, "games": 1561}, "108": {"win_rate": 0.491, "games": 928}, "16": {"win_rate": 0.474, "games": 959}, "32": {"win_rate": 0.512, "games": 516}, "39": {"win_rate": 0.482, "games": 2384}, "34": {"win_rate": 0.436, "games": 374}, "17": {"win_rate": 0.456, "games": 1041}, "8": {"win_rate": 0.505, "games": 2104}, "18": {"win_rate": 0.489, "games": 503}, "22": {"win_rate": 0.49, "games": 1502}, "73": {"win_rate": 0.495, "games": 2057}, "136": {"win_rate": 0.478, "games": 412}, "60": {"win_rate": 0.511, "games": 1275}, "29": {"win_rate": 0.509, "games": 2367}, "119": {"win_rate": 0.471, "games": 329}, "85": {"win_rate": 0.51, "games": 840}, "5": {"win_rate": 0.49, "games": 628}, "1": {"win_rate": 0.465, "games": 1330}, "92": {"win_rate": 0.541, "games": 159}, "74": {"win_rate": 0.518, "games": 2572}, "75": {"win_rate": 0.48, "games": 808}, "123": {"win_rate": 0.477, "games": 774}, "31": {"win_rate": 0.496, "games": 782}, "6": {"win_rate": 0.487, "games": 1306}, "70": {"win_rate": 0.46, "games": 1145}, "45": {"win_rate": 0.491, "games": 283}, "44": {"win_rate": 0.474, "games": 1599}, "129": {"win_rate": 0.428, "games": 1400}, "26": {"win_rate": 0.475, "games": 2104}, "19": {"win_rate": 0.435, "games": 1071}, "102": {"win_rate": 0.487, "games": 302}, "4": {"win_rate": 0.501, "games": 489}, "112": {"win_rate": 0.495, "games": 285}, "103": {"win_rate": 0.506, "games": 85}, "105": {"win_rate": 0.496, "games": 793}, "68": {"win_rate": 0.461, "games": 406}, "49": {"win_rate": 0.463, "games": 527}, "104": {"win_rate": 0.501, "games": 1991}, "12": {"win_rate": 0.511, "games": 980}, "95": {"win_rate": 0.475, "games": 217}, "30": {"win_rate": 0.475, "games": 1007}, "13": {"win_rate": 0.444, "games": 701}, "128": {"win_rate": 0.446, "games": 514}, "97": {"win_rate": 0.464, "games": 1523}, "145": {"win_rate": 0.455, "games": 646}, "9": {"win_rate": 0.468, "games": 656}, "57": {"win_rate": 0.458, "games": 271}, "52": {"win_rate": 0.457, "games": 411}, "23": {"win_rate": 0.466, "games": 678}, "88": {"win_rate": 0.476, "games": 695}, "101": {"win_rate": 0.45, "games": 1030}, "131": {"win_rate": 0.449, "games": 292}, "137": {"win_rate": 0.472, "games": 650}, "51": {"win_rate": 0.44, "games": 282}, "61": {"win_rate": 0.469, "games": 213}, "111": {"win_rate": 0.468, "games": 205}, "7": {"win_rate": 0.464, "games": 1491}, "91": {"win_rate": 0.466, "games": 191}, "50": {"win_rate": 0.467, "games": 197}, "72": {"win_rate": 0.383, "games": 402}}}, "CRUSADER_ARCHON": {"vs": {"93": {"win_rate": 0.537, "games": 3048}, "66": {"win_rate": 0.559, "games": 102}, "51": {"win_rate": 0.558, "games": 563}, "91": {"win_rate": 0.503, "games": 501}, "76": {"win_rate": 0.537, "games": 1033}, "92": {"win_rate": 0.477, "games": 239}, "131": {"win_rate": 0.54, "games": 644}, "1": {"win_rate": 0.545, "games": 2031}, "70": {"win_rate": 0.552, "games": 1345}, "155": {"win_rate": 0.54, "games": 311}, "32": {"win_rate": 0.497, "games": 962}, "36": {"win_rate": 0.497, "games": 2636}, "137": {"win_rate": 0.505, "games": 707}, "7": {"win_rate": 0.517, "games": 2492}, "100": {"win_rate": 0.532, "games": 1253}, "96": {"win_rate": 0.529, "games": 1075}, "111": {"win_rate": 0.516, "games": 581}, "34": {"win_rate": 0.565, "games": 519}, "52": {"win_rate": 0.526, "games": 616}, "110": {"win_rate": 0.481, "games": 1280}, "112": {"win_rate": 0.511, "games": 677}, "86": {"win_rate": 0.507, "games": 4855}, "123": {"win_rate": 0.519, "games": 1699}, "18": {"win_rate": 0.51, "games": 789}, "102": {"win_rate": 0.492, "games": 587}, "41": {"win_rate": 0.508, "games": 2183}, "136": {"win_rate": 0.517, "games": 673}, "13": {"win_rate": 0.529, "games": 838}, "88": {"win_rate": 0.491, "games": 1350}, "71": {"win_rate": 0.499, "games": 4160}, "16": {"win_rate": 0.508, "games": 1264}, "17": {"win_rate": 0.539, "games": 1226}, "61": {"win_rate": 0.493, "games": 430}, "126": {"win_rate": 0.497, "games": 1339}, "2": {"win_rate": 0.477, "games": 3332}, "14": {"win_rate": 0.499, "games": 5777}, "37": {"win_rate": 0.497, "games": 1727}, "5": {"win_rate": 0.49, "games": 2661}, "23": {"win_rate": 0.502, "games": 990}, "73": {"win_rate": 0.491, "games": 2726}, "129": {"win_rate": 0.557, "games": 1603}, "68": {"win_rate": 0.505, "games": 1399}, "84": {"win_rate": 0.487, "games": 3870}, "29": {"win_rate": 0.474, "games": 3091}, "74": {"win_rate": 0.474, "games": 3796}, "89": {"win_rate": 0.494, "games": 269}, "25": {"win_rate": 0.515, "games": 2568}, "75": {"win_rate": 0.491, "games": 2678}, "26": {"win_rate": 0.503, "games": 5978}, "59": {"win_rate": 0.504, "games": 1037}, "135": {"win_rate": 0.465, "games": 1404}, "48": {"win_rate": 0.483, "games": 1546}, "120": {"win_rate": 0.505, "games": 1478}, "67": {"win_rate": 0.452, "games": 2137}, "105": {"win_rate": 0.468, "games": 1914}, "79": {"win_rate": 0.534, "games": 558}, "54": {"win_rate": 0.468, "games": 2786}, "33": {"win_rate": 0.495, "games": 463}, "46": {"win_rate": 0.531, "games": 1005}, "106": {"win_rate": 0.505, "games": 1383}, "99": {"win_rate": 0.495, "games": 1670}, "83": {"win_rate": 0.501, "games": 465}, "30": {"win_rate": 0.482, "games": 3856}, "31": {"win_rate": 0.475, "games": 2538}, "69": {"win_rate": 0.534, "games": 1512}, "15": {"win_rate": 0.494, "games": 1262}, "98": {"win_rate": 0.55, "games": 565}, "60": {"win_rate": 0.475, "games": 1522}, "8": {"win_rate": 0.473, "games": 3330}, "101": {"win_rate": 0.497, "games": 2593}, "28": {"win_rate": 0.478, "games": 1873}, "145": {"win_rate": 0.505, "games": 687}, "121": {"win_rate": 0.472, "games": 986}, "21": {"win_rate": 0.514, "games": 2137}, "9": {"win_rate": 0.489, "games": 1416}, "12": {"win_rate": 0.445, "games": 1385}, "42": {"win_rate": 0.445, "games": 2876}, "80": {"win_rate": 0.444, "games": 473}, "27": {"win_rate": 0.463, "games": 3629}, "50": {"win_rate": 0.472, "games": 843}, "72": {"win_rate": 0.552, "games": 768}, "11": {"win_rate": 0.507, "games": 2580}, "95": {"win_rate": 0.481, "games": 351}, "63": {"win_rate": 0.52, "games": 1845}, "19": {"win_rate": 0.528, "games": 1442}, "108": {"win_rate": 0.468, "games": 1231}, "4": {"win_rate": 0.462, "games": 731}, "81": {"win_rate": 0.483, "games": 748}, "56": {"win_rate": 0.468, "games": 891}, "138": {"win_rate": 0.493, "games": 1146}, "64": {"win_rate": 0.517, "games": 2469}, "39": {"win_rate": 0.5, "games": 3045}, "65": {"win_rate": 0.488, "games": 566}, "78": {"win_rate": 0.479, "games": 242}, "3": {"win_rate": 0.476, "games": 412}, "114": {"win_rate": 0.52, "games": 1833}, "47": {"win_rate": 0.487, "games": 1480}, "62": {"win_rate": 0.478, "games": 803}, "103": {"win_rate": 0.473, "games": 165}, "104": {"win_rate": 0.449, "games": 3342}, "109": {"win_rate": 0.484, "games": 415}, "57": {"win_rate": 0.484, "games": 492}, "44": {"win_rate": 0.474, "games": 2731}, "85": {"win_rate": 0.454, "games": 1780}, "49": {"win_rate": 0.484, "games": 1001}, "10": {"win_rate": 0.494, "games": 686}, "113": {"win_rate": 0.46, "games": 528}, "38": {"win_rate": 0.496, "games": 1381}, "94": {"win_rate": 0.46, "games": 948}, "22": {"win_rate": 0.465, "games": 3206}, "53": {"win_rate": 0.541, "games": 1429}, "45": {"win_rate": 0.462, "games": 728}, "6": {"win_rate": 0.466, "games": 2303}, "107": {"win_rate": 0.466, "games": 562}, "35": {"win_rate": 0.468, "games": 4395}, "97": {"win_rate": 0.483, "games": 2127}, "90": {"win_rate": 0.444, "games": 832}, "20": {"win_rate": 0.437, "games": 1581}, "128": {"win_rate": 0.488, "games": 1072}, "40": {"win_rate": 0.478, "games": 3112}, "55": {"win_rate": 0.467, "games": 291}, "119": {"win_rate": 0.479, "games": 856}, "82": {"win_rate": 0.445, "games": 447}, "58": {"win_rate": 0.464, "games": 330}, "43": {"win_rate": 0.467, "games": 867}, "77": {"win_rate": 0.449, "games": 118}}, "with": {"109": {"win_rate": 0.538, "games": 444}, "80": {"win_rate": 0.576, "games": 484}, "92": {"win_rate": 0.578, "games": 185}, "51": {"win_rate": 0.502, "games": 400}, "58": {"win_rate": 0.514, "games": 222}, "89": {"win_rate": 0.532, "games": 299}, "28": {"win_rate": 0.536, "games": 1939}, "82": {"win_rate": 0.532, "games": 391}, "36": {"win_rate": 0.537, "games": 2824}, "13": {"win_rate": 0.494, "games": 808}, "76": {"win_rate": 0.505, "games": 1002}, "123": {"win_rate": 0.504, "games": 921}, "61": {"win_rate": 0.524, "games": 351}, "138": {"win_rate": 0.505, "games": 1045}, "48": {"win_rate": 0.525, "games": 1488}, "98": {"win_rate": 0.454, "games": 621}, "63": {"win_rate": 0.477, "games": 1744}, "120": {"win_rate": 0.5, "games": 1389}, "102": {"win_rate": 0.523, "games": 444}, "35": {"win_rate": 0.507, "games": 3845}, "44": {"win_rate": 0.51, "games": 2609}, "91": {"win_rate": 0.529, "games": 223}, "77": {"win_rate": 0.478, "games": 136}, "39": {"win_rate": 0.49, "games": 2898}, "8": {"win_rate": 0.522, "games": 2997}, "56": {"win_rate": 0.521, "games": 883}, "52": {"win_rate": 0.488, "games": 529}, "126": {"win_rate": 0.509, "games": 1159}, "85": {"win_rate": 0.525, "games": 1419}, "34": {"win_rate": 0.45, "games": 462}, "95": {"win_rate": 0.508, "games": 398}, "33": {"win_rate": 0.502, "games": 303}, "42": {"win_rate": 0.544, "games": 2868}, "43": {"win_rate": 0.484, "games": 818}, "45": {"win_rate": 0.511, "games": 425}, "108": {"win_rate": 0.518, "games": 1197}, "78": {"win_rate": 0.504, "games": 248}, "10": {"win_rate": 0.481, "games": 718}, "83": {"win_rate": 0.493, "games": 225}, "54": {"win_rate": 0.525, "games": 2857}, "60": {"win_rate": 0.515, "games": 1439}, "30": {"win_rate": 0.509, "games": 1799}, "84": {"win_rate": 0.51, "games": 2402}, "17": {"win_rate": 0.461, "games": 1324}, "114": {"win_rate": 0.457, "games": 1809}, "65": {"win_rate": 0.491, "games": 432}, "21": {"win_rate": 0.471, "games": 1667}, "86": {"win_rate": 0.497, "games": 2859}, "119": {"win_rate": 0.475, "games": 512}, "37": {"win_rate": 0.499, "games": 780}, "81": {"win_rate": 0.496, "games": 702}, "93": {"win_rate": 0.493, "games": 3357}, "29": {"win_rate": 0.519, "games": 2997}, "57": {"win_rate": 0.487, "games": 378}, "110": {"win_rate": 0.521, "games": 926}, "131": {"win_rate": 0.477, "games": 281}, "27": {"win_rate": 0.516, "games": 1529}, "94": {"win_rate": 0.505, "games": 884}, "47": {"win_rate": 0.484, "games": 1376}, "106": {"win_rate": 0.48, "games": 1429}, "26": {"win_rate": 0.486, "games": 3140}, "67": {"win_rate": 0.533, "games": 2087}, "12": {"win_rate": 0.533, "games": 1519}, "100": {"win_rate": 0.471, "games": 872}, "19": {"win_rate": 0.448, "games": 1172}, "5": {"win_rate": 0.5, "games": 1096}, "75": {"win_rate": 0.496, "games": 1477}, "15": {"win_rate": 0.486, "games": 1318}, "14": {"win_rate": 0.491, "games": 3990}, "71": {"win_rate": 0.492, "games": 3017}, "31": {"win_rate": 0.505, "games": 1065}, "2": {"win_rate": 0.512, "games": 3472}, "104": {"win_rate": 0.515, "games": 3263}, "135": {"win_rate": 0.518, "games": 1311}, "107": {"win_rate": 0.489, "games": 421}, "103": {"win_rate": 0.491, "games": 106}, "11": {"win_rate": 0.466, "games": 2327}, "40": {"win_rate": 0.471, "games": 1704}, "74": {"win_rate": 0.511, "games": 3296}, "22": {"win_rate": 0.494, "games": 2083}, "16": {"win_rate": 0.481, "games": 1237}, "6": {"win_rate": 0.489, "games": 2107}, "97": {"win_rate": 0.469, "games": 1801}, "20": {"win_rate": 0.511, "games": 921}, "23": {"win_rate": 0.483, "games": 949}, "1": {"win_rate": 0.463, "games": 2152}, "64": {"win_rate": 0.451, "games": 1112}, "18": {"win_rate": 0.481, "games": 796}, "25": {"win_rate": 0.467, "games": 2299}, "99": {"win_rate": 0.482, "games": 1698}, "136": {"win_rate": 0.473, "games": 556}, "137": {"win_rate": 0.493, "games": 710}, "79": {"win_rate": 0.442, "games": 215}, "73": {"win_rate": 0.489, "games": 2480}, "70": {"win_rate": 0.451, "games": 1500}, "145": {"win_rate": 0.464, "games": 716}, "69": {"win_rate": 0.437, "games": 1528}, "96": {"win_rate": 0.461, "games": 1028}, "53": {"win_rate": 0.411, "games": 1003}, "49": {"win_rate": 0.468, "games": 983}, "113": {"win_rate": 0.491, "games": 491}, "59": {"win_rate": 0.469, "games": 908}, "72": {"win_rate": 0.411, "games": 659}, "7": {"win_rate": 0.472, "games": 1954}, "9": {"win_rate": 0.474, "games": 882}, "41": {"win_rate": 0.473, "games": 2262}, "62": {"win_rate": 0.473, "games": 528}, "50": {"win_rate": 0.486, "games": 323}, "101": {"win_rate": 0.465, "games": 1593}, "105": {"win_rate": 0.495, "games": 1107}, "38": {"win_rate": 0.446, "games": 1333}, "68": {"win_rate": 0.462, "games": 676}, "121": {"win_rate": 0.483, "games": 402}, "4": {"win_rate": 0.488, "games": 765}, "129": {"win_rate": 0.409, "games": 1627}, "32": {"win_rate": 0.488, "games": 884}, "55": {"win_rate": 0.456, "games": 283}, "88": {"win_rate": 0.476, "games": 934}, "46": {"win_rate": 0.425, "games": 943}, "155": {"win_rate": 0.443, "games": 219}, "3": {"win_rate": 0.459, "games": 181}, "90": {"win_rate": 0.471, "games": 577}, "111": {"win_rate": 0.432, "games": 294}, "128": {"win_rate": 0.404, "games": 666}, "112": {"win_rate": 0.422, "games": 329}, "66": {"win_rate": 0.341, "games": 41}}}, "HERALD_GUARDIAN": {"vs": {"66": {"win_rate": 0.612, "games": 49}, "103": {"win_rate": 0.518, "games": 112}, "93": {"win_rate": 0.525, "games": 1894}, "128": {"win_rate": 0.544, "games": 572}, "55": {"win_rate": 0.532, "games": 203}, "119": {"win_rate": 0.552, "games": 601}, "52": {"win_rate": 0.519, "games": 351}, "10": {"win_rate": 0.537, "games": 449}, "129": {"win_rate": 0.566, "games": 772}, "145": {"win_rate": 0.537, "games": 361}, "108": {"win_rate": 0.49, "games": 669}, "90": {"win_rate": 0.516, "games": 483}, "97": {"win_rate": 0.531, "games": 939}, "70": {"win_rate": 0.546, "games": 782}, "61": {"win_rate": 0.496, "games": 391}, "71": {"win_rate": 0.496, "games": 2588}, "47": {"win_rate": 0.524, "games": 1314}, "110": {"win_rate": 0.486, "games": 607}, "96": {"win_rate": 0.509, "games": 640}, "69": {"win_rate": 0.549, "games": 818}, "65": {"win_rate": 0.519, "games": 268}, "126": {"win_rate": 0.502, "games": 600}, "85": {"win_rate": 0.485, "games": 1317}, "1": {"win_rate": 0.519, "games": 1436}, "43": {"win_rate": 0.525, "games": 646}, "7": {"win_rate": 0.509, "games": 1606}, "2": {"win_rate": 0.465, "games": 2193}, "9": {"win_rate": 0.489, "games": 959}, "112": {"win_rate": 0.507, "games": 444}, "40": {"win_rate": 0.515, "games": 1791}, "107": {"win_rate": 0.517, "games": 263}, "28": {"win_rate": 0.495, "games": 1234}, "89": {"win_rate": 0.486, "games": 284}, "32": {"win_rate": 0.472, "games": 925}, "26": {"win_rate": 0.501, "games": 3667}, "18": {"win_rate": 0.5, "games": 662}, "79": {"win_rate": 0.55, "games": 260}, "99": {"win_rate": 0.466, "games": 1486}, "77": {"win_rate": 0.543, "games": 105}, "11": {"win_rate": 0.51, "games": 1481}, "102": {"win_rate": 0.48, "games": 346}, "64": {"win_rate": 0.51, "games": 1327}, "34": {"win_rate": 0.559, "games": 324}, "36": {"win_rate": 0.463, "games": 1834}, "27": {"win_rate": 0.469, "games": 2458}, "8": {"win_rate": 0.476, "games": 2089}, "17": {"win_rate": 0.525, "games": 712}, "86": {"win_rate": 0.5, "games": 2155}, "19": {"win_rate": 0.54, "games": 669}, "62": {"win_rate": 0.491, "games": 552}, "131": {"win_rate": 0.508, "games": 321}, "41": {"win_rate": 0.491, "games": 1391}, "135": {"win_rate": 0.46, "games": 626}, "68": {"win_rate": 0.484, "games": 832}, "100": {"win_rate": 0.525, "games": 541}, "73": {"win_rate": 0.469, "games": 1306}, "75": {"win_rate": 0.468, "games": 1791}, "14": {"win_rate": 0.479, "games": 3748}, "39": {"win_rate": 0.51, "games": 1644}, "80": {"win_rate": 0.462, "games": 299}, "37": {"win_rate": 0.475, "games": 1111}, "46": {"win_rate": 0.524, "games": 675}, "114": {"win_rate": 0.526, "games": 1019}, "121": {"win_rate": 0.466, "games": 491}, "155": {"win_rate": 0.513, "games": 154}, "22": {"win_rate": 0.469, "games": 2071}, "30": {"win_rate": 0.466, "games": 2525}, "54": {"win_rate": 0.464, "games": 1492}, "74": {"win_rate": 0.465, "games": 2128}, "4": {"win_rate": 0.46, "games": 680}, "12": {"win_rate": 0.451, "games": 1096}, "84": {"win_rate": 0.462, "games": 2899}, "5": {"win_rate": 0.457, "games": 1939}, "57": {"win_rate": 0.496, "games": 268}, "51": {"win_rate": 0.511, "games": 329}, "15": {"win_rate": 0.485, "games": 961}, "16": {"win_rate": 0.472, "games": 833}, "123": {"win_rate": 0.491, "games": 1077}, "29": {"win_rate": 0.454, "games": 1801}, "104": {"win_rate": 0.452, "games": 2137}, "25": {"win_rate": 0.509, "games": 1762}, "58": {"win_rate": 0.493, "games": 349}, "49": {"win_rate": 0.482, "games": 800}, "91": {"win_rate": 0.461, "games": 319}, "82": {"win_rate": 0.469, "games": 292}, "60": {"win_rate": 0.479, "games": 678}, "33": {"win_rate": 0.477, "games": 348}, "76": {"win_rate": 0.502, "games": 582}, "6": {"win_rate": 0.484, "games": 1703}, "48": {"win_rate": 0.462, "games": 974}, "137": {"win_rate": 0.463, "games": 415}, "50": {"win_rate": 0.474, "games": 496}, "21": {"win_rate": 0.508, "games": 1597}, "105": {"win_rate": 0.449, "games": 1268}, "44": {"win_rate": 0.457, "games": 1997}, "120": {"win_rate": 0.495, "games": 556}, "23": {"win_rate": 0.485, "games": 565}, "94": {"win_rate": 0.449, "games": 673}, "67": {"win_rate": 0.411, "games": 1492}, "83": {"win_rate": 0.472, "games": 309}, "72": {"win_rate": 0.543, "games": 422}, "95": {"win_rate": 0.45, "games": 358}, "56": {"win_rate": 0.459, "games": 798}, "53": {"win_rate": 0.52, "games": 1085}, "109": {"win_rate": 0.483, "games": 298}, "20": {"win_rate": 0.434, "games": 947}, "45": {"win_rate": 0.468, "games": 474}, "35": {"win_rate": 0.456, "games": 3260}, "88": {"win_rate": 0.443, "games": 745}, "101": {"win_rate": 0.467, "games": 1708}, "138": {"win_rate": 0.466, "games": 712}, "31": {"win_rate": 0.437, "games": 1469}, "113": {"win_rate": 0.448, "games": 353}, "3": {"win_rate": 0.462, "games": 266}, "42": {"win_rate": 0.401, "games": 1820}, "13": {"win_rate": 0.5, "games": 436}, "63": {"win_rate": 0.486, "games": 1240}, "78": {"win_rate": 0.444, "games": 126}, "38": {"win_rate": 0.471, "games": 734}, "81": {"win_rate": 0.447, "games": 606}, "59": {"win_rate": 0.478, "games": 735}, "98": {"win_rate": 0.511, "games": 327}, "106": {"win_rate": 0.46, "games": 668}, "111": {"win_rate": 0.454, "games": 313}, "136": {"win_rate": 0.454, "games": 441}, "92": {"win_rate": 0.398, "games": 171}}, "with": {"66": {"win_rate": 0.5, "games": 26}, "10": {"win_rate": 0.516, "games": 384}, "79": {"win_rate": 0.483, "games": 147}, "113": {"win_rate": 0.535, "games": 342}, "103": {"win_rate": 0.53, "games": 83}, "81": {"win_rate": 0.517, "games": 685}, "82": {"win_rate": 0.522, "games": 293}, "48": {"win_rate": 0.524, "games": 945}, "138": {"win_rate": 0.502, "games": 604}, "54": {"win_rate": 0.528, "games": 1565}, "20": {"win_rate": 0.534, "games": 567}, "63": {"win_rate": 0.473, "games": 1147}, "95": {"win_rate": 0.52, "games": 344}, "9": {"win_rate": 0.514, "games": 646}, "72": {"win_rate": 0.43, "games": 388}, "102": {"win_rate": 0.516, "games": 306}, "55": {"win_rate": 0.492, "games": 130}, "46": {"win_rate": 0.465, "games": 587}, "101": {"win_rate": 0.497, "games": 1008}, "50": {"win_rate": 0.502, "games": 219}, "8": {"win_rate": 0.516, "games": 2000}, "35": {"win_rate": 0.506, "games": 2927}, "112": {"win_rate": 0.49, "games": 208}, "84": {"win_rate": 0.519, "games": 1779}, "15": {"win_rate": 0.495, "games": 940}, "129": {"win_rate": 0.446, "games": 762}, "11": {"win_rate": 0.48, "games": 1403}, "76": {"win_rate": 0.472, "games": 634}, "108": {"win_rate": 0.515, "games": 637}, "51": {"win_rate": 0.467, "games": 246}, "42": {"win_rate": 0.551, "games": 1867}, "62": {"win_rate": 0.493, "games": 363}, "47": {"win_rate": 0.476, "games": 1226}, "90": {"win_rate": 0.485, "games": 291}, "56": {"win_rate": 0.499, "games": 731}, "104": {"win_rate": 0.522, "games": 2001}, "106": {"win_rate": 0.475, "games": 653}, "69": {"win_rate": 0.448, "games": 743}, "136": {"win_rate": 0.475, "games": 360}, "21": {"win_rate": 0.457, "games": 1197}, "7": {"win_rate": 0.482, "games": 1331}, "109": {"win_rate": 0.471, "games": 323}, "98": {"win_rate": 0.429, "games": 359}, "93": {"win_rate": 0.493, "games": 1957}, "135": {"win_rate": 0.517, "games": 633}, "78": {"win_rate": 0.496, "games": 113}, "61": {"win_rate": 0.498, "games": 333}, "99": {"win_rate": 0.515, "games": 1412}, "74": {"win_rate": 0.505, "games": 1663}, "26": {"win_rate": 0.481, "games": 1907}, "39": {"win_rate": 0.462, "games": 1551}, "110": {"win_rate": 0.505, "games": 406}, "89": {"win_rate": 0.496, "games": 268}, "12": {"win_rate": 0.517, "games": 1053}, "92": {"win_rate": 0.504, "games": 129}, "96": {"win_rate": 0.481, "games": 626}, "28": {"win_rate": 0.486, "games": 1238}, "53": {"win_rate": 0.429, "games": 735}, "65": {"win_rate": 0.469, "games": 228}, "88": {"win_rate": 0.502, "games": 468}, "30": {"win_rate": 0.5, "games": 1175}, "73": {"win_rate": 0.5, "games": 1252}, "36": {"win_rate": 0.51, "games": 1802}, "3": {"win_rate": 0.478, "games": 138}, "31": {"win_rate": 0.502, "games": 671}, "114": {"win_rate": 0.44, "games": 1014}, "6": {"win_rate": 0.473, "games": 1648}, "1": {"win_rate": 0.463, "games": 1410}, "80": {"win_rate": 0.502, "games": 293}, "5": {"win_rate": 0.504, "games": 910}, "91": {"win_rate": 0.496, "games": 141}, "85": {"win_rate": 0.495, "games": 1007}, "17": {"win_rate": 0.444, "games": 734}, "86": {"win_rate": 0.468, "games": 1348}, "14": {"win_rate": 0.484, "games": 2657}, "71": {"win_rate": 0.486, "games": 1748}, "145": {"win_rate": 0.45, "games": 371}, "75": {"win_rate": 0.493, "games": 977}, "60": {"win_rate": 0.474, "games": 661}, "40": {"win_rate": 0.457, "games": 999}, "27": {"win_rate": 0.494, "games": 1113}, "23": {"win_rate": 0.458, "games": 579}, "49": {"win_rate": 0.469, "games": 840}, "29": {"win_rate": 0.499, "games": 1735}, "70": {"win_rate": 0.432, "games": 820}, "119": {"win_rate": 0.437, "games": 332}, "68": {"win_rate": 0.473, "games": 480}, "43": {"win_rate": 0.445, "games": 573}, "58": {"win_rate": 0.456, "games": 226}, "120": {"win_rate": 0.445, "games": 508}, "4": {"win_rate": 0.491, "games": 658}, "126": {"win_rate": 0.469, "games": 539}, "44": {"win_rate": 0.482, "games": 2003}, "2": {"win_rate": 0.5, "games": 2225}, "32": {"win_rate": 0.488, "games": 789}, "16": {"win_rate": 0.474, "games": 730}, "25": {"win_rate": 0.436, "games": 1474}, "57": {"win_rate": 0.45, "games": 262}, "38": {"win_rate": 0.441, "games": 741}, "52": {"win_rate": 0.457, "games": 311}, "41": {"win_rate": 0.458, "games": 1436}, "59": {"win_rate": 0.43, "games": 642}, "13": {"win_rate": 0.412, "games": 398}, "128": {"win_rate": 0.433, "games": 372}, "22": {"win_rate": 0.471, "games": 1391}, "64": {"win_rate": 0.438, "games": 704}, "94": {"win_rate": 0.475, "games": 612}, "155": {"win_rate": 0.426, "games": 108}, "97": {"win_rate": 0.428, "games": 720}, "107": {"win_rate": 0.432, "games": 199}, "37": {"win_rate": 0.461, "games": 570}, "77": {"win_rate": 0.402, "games": 87}, "19": {"win_rate": 0.4, "games": 587}, "67": {"win_rate": 0.506, "games": 1452}, "105": {"win_rate": 0.472, "games": 738}, "123": {"win_rate": 0.437, "games": 572}, "137": {"win_rate": 0.456, "games": 399}, "34": {"win_rate": 0.378, "games": 296}, "45": {"win_rate": 0.438, "games": 324}, "18": {"win_rate": 0.436, "games": 674}, "131": {"win_rate": 0.423, "games": 156}, "33": {"win_rate": 0.438, "games": 224}, "100": {"win_rate": 0.396, "games": 404}, "83": {"win_rate": 0.423, "games": 175}, "111": {"win_rate": 0.407, "games": 140}, "121": {"win_rate": 0.436, "games": 257}}}}